{"info":{"short-canon":"ot","canon":"Old Testament","name":"Habakkuk","desc":"The Book of Habakkuk","interlinear":true},"1":{"1":[[["ham\u00b7ma\u015b\u00b7\u015b\u0101","\u05d4\u05b7\u05de\u05b7\u05bc\u05e9\u05b8\u05c2\u05d0\u0599\u202a\u202c\u202a\u202c","the burden"],["\u2019\u0103\u00b7\u0161er","\u05d0\u05b2\u05e9\u05b6\u05c1\u05a3\u05e8","which"],["\u1e25\u0101\u00b7z\u0101h,","\u05d7\u05b8\u05d6\u05b8\u0594\u05d4","saw"],["\u1e25\u0103\u00b7\u1e07aq\u00b7q\u016bq","\u05d7\u05b2\u05d1\u05b7\u05e7\u05bc\u0596\u05d5\u05bc\u05e7","Habakkuk"],["han\u00b7n\u0101\u00b7\u1e07\u00ee.","\u05d4\u05b7\u05e0\u05b8\u05bc\u05d1\u05b4\u05bd\u05d9\u05d0\u05c3","the prophet"],["",".",""]],"Habakkuk's Complaint",null,"Psalm 13:1-6"],"2":[[["\u2018a\u1e0f-","\u05e2\u05b7\u05d3\u05be","How"],["\u2019\u0101\u00b7n\u0101h","\u05d0\u05b8\u05a7\u05e0\u05b8\u05d4","long"],["Yah\u00b7weh","\u05d9\u05b0\u05d4\u05d5\u05b8\u059b\u05d4","Yahweh"],["",",",""],["\u0161iw\u00b7wa\u2018\u00b7t\u00ee","\u05e9\u05b4\u05c1\u05d5\u05b7\u05bc\u0596\u05e2\u05b0\u05ea\u05b4\u05bc\u05d9","shall I cry"],["",",",""],["w\u0259\u00b7l\u014d","\u05d5\u05b0\u05dc\u05b9\u05a3\u05d0","and not"],["\u1e6fi\u0161\u00b7m\u0101\u2018;","\u05ea\u05b4\u05e9\u05b0\u05c1\u05de\u05b8\u0591\u05e2","You will hear"],["","!",""],["\u2019ez\u00b7\u2018aq","\u05d0\u05b6\u05d6\u05b0\u05e2\u05b7\u05a5\u05e7","Even cry out"],["\u2019\u00ea\u00b7le\u00b7\u1e35\u0101","\u05d0\u05b5\u05dc\u05b6\u059b\u05d9\u05da\u05b8","to You"],["\u1e25\u0101\u00b7m\u0101s","\u05d7\u05b8\u05de\u05b8\u0596\u05e1","Violence"],["",",",""],["w\u0259\u00b7l\u014d","\u05d5\u05b0\u05dc\u05b9\u05a5\u05d0","and not"],["\u1e6f\u014d\u00b7w\u014d\u00b7\u0161\u00ee\u00b7a\u2018.","\u05ea\u05d5\u05b9\u05e9\u05b4\u05bd\u05c1\u05d9\u05e2\u05b7\u05c3","You will save"],["","!",""]],"Habakkuk's Complaint",null,"Psalm 13:1-6"],"3":[[["l\u0101m\u00b7m\u0101h","\u05dc\u05b8\u05a3\u05de\u05b8\u05bc\u05d4","why"],["\u1e6far\u00b7\u2019\u00ea\u00b7n\u00ee","\u05ea\u05b7\u05e8\u05b0\u05d0\u05b5\u05a4\u05e0\u05b4\u05d9","do You show me"],["\u2019\u0101\u00b7wen","\u05d0\u05b8\u0599\u05d5\u05b6\u05df\u0599","iniquity"],["",",",""],["w\u0259\u00b7\u2018\u0101\u00b7m\u0101l","\u05d5\u05b0\u05e2\u05b8\u05de\u05b8\u05a3\u05dc","and trouble"],["","?",""],["tab\u00b7b\u00ee\u1e6d,","\u05ea\u05b7\u05bc\u05d1\u05b4\u05bc\u0594\u05d9\u05d8","cause [me] to see"],["w\u0259\u00b7\u0161\u014d\u1e0f","\u05d5\u05b0\u05e9\u05b9\u05c1\u05a5\u05d3","for plundering"],["w\u0259\u00b7\u1e25\u0101\u00b7m\u0101s","\u05d5\u05b0\u05d7\u05b8\u05de\u05b8\u0596\u05e1","and violence"],["l\u0259\u00b7ne\u1e21\u00b7d\u00ee;","\u05dc\u05b0\u05e0\u05b6\u05d2\u05b0\u05d3\u05b4\u05bc\u0591\u05d9","[are] before me"],["way\u00b7h\u00ee","\u05d5\u05b7\u05d9\u05b0\u05d4\u05b4\u05a7\u05d9","and there is"],["r\u00ee\u1e07","\u05e8\u05b4\u05a6\u05d9\u05d1","strife"],["\u016b\u00b7m\u0101\u00b7\u1e0f\u014d\u00b7wn","\u05d5\u05bc\u05de\u05b8\u05d3\u0596\u05d5\u05b9\u05df","and contention"],["yi\u015b\u00b7\u015b\u0101.","\u05d9\u05b4\u05e9\u05b8\u05bc\u05bd\u05c2\u05d0\u05c3","arises"],["",".",""]],"Habakkuk's Complaint",null,"Psalm 13:1-6"],"4":[[["\u2018al-","\u05e2\u05b7\u05dc\u05be","Upon"],["k\u00ean","\u05db\u05b5\u05bc\u05df\u0599","thus"],["t\u0101\u00b7p\u0304\u016b\u1e21","\u05ea\u05b8\u05bc\u05e4\u05a3\u05d5\u05bc\u05d2","is powerless"],["",",",""],["t\u014d\u00b7w\u00b7r\u0101h,","\u05ea\u05bc\u05d5\u05b9\u05e8\u05b8\u0594\u05d4","the law"],["w\u0259\u00b7l\u014d-","\u05d5\u05b0\u05dc\u05b9\u05bd\u05d0\u05be","and never"],["y\u00ea\u00b7\u1e63\u00ea","\u05d9\u05b5\u05e6\u05b5\u05a5\u05d0","goes forth"],["",".",""],["l\u0101\u00b7ne\u00b7\u1e63a\u1e25","\u05dc\u05b8\u05e0\u05b6\u0596\u05e6\u05b7\u05d7","Never"],["mi\u0161\u00b7p\u0101\u1e6d;","\u05de\u05b4\u05e9\u05b0\u05c1\u05e4\u05b8\u05bc\u0591\u05d8","justice"],["k\u00ee","\u05db\u05b4\u05bc\u05a4\u05d9","for"],["r\u0101\u00b7\u0161\u0101\u2018","\u05e8\u05b8\u05e9\u05b8\u05c1\u05e2\u0599","the wicked"],["ma\u1e35\u00b7t\u00eer","\u05de\u05b7\u05db\u05b0\u05ea\u05b4\u05bc\u05a3\u05d9\u05e8","surround"],["\u2019e\u1e6f-","\u05d0\u05b6\u05ea\u05be",""],["ha\u1e63\u00b7\u1e63ad\u00b7d\u00eeq,","\u05d4\u05b7\u05e6\u05b7\u05bc\u05d3\u05b4\u05bc\u0594\u05d9\u05e7","the righteous"],["","-",""],["\u2018al-","\u05e2\u05b7\u05dc\u05be","upon"],["k\u00ean","\u05db\u05b5\u05bc\u059b\u05df","thus"],["y\u00ea\u00b7\u1e63\u00ea","\u05d9\u05b5\u05e6\u05b5\u05a5\u05d0","proceeds"],["mi\u0161\u00b7p\u0101\u1e6d","\u05de\u05b4\u05e9\u05b0\u05c1\u05e4\u05b8\u05bc\u0596\u05d8","judgment"],["m\u0259\u00b7\u2018uq\u00b7q\u0101l.","\u05de\u05b0\u05e2\u05bb\u05e7\u05b8\u05bc\u05bd\u05dc\u05c3","perverse"],["",".",""]],"The Lord's Answer"],"5":[[["r\u0259\u00b7\u2019\u016b","\u05e8\u05b0\u05d0\u05a4\u05d5\u05bc","Look"],["\u1e07ag\u00b7g\u014d\u00b7w\u00b7yim","\u05d1\u05b7\u05d2\u05bc\u05d5\u05b9\u05d9\u05b4\u05dd\u0599","among the nations"],["",",",""],["w\u0259\u00b7hab\u00b7b\u00ee\u00b7\u1e6d\u016b,","\u05d5\u05b0\u05bd\u05d4\u05b7\u05d1\u05b4\u05bc\u0594\u05d9\u05d8\u05d5\u05bc","and watch"],["",",",""],["w\u0259\u00b7hit\u00b7tam\u00b7m\u0259\u00b7h\u016b","\u05d5\u05b0\u05d4\u05b4\u05bd\u05ea\u05b7\u05bc\u05de\u05b0\u05bc\u05d4\u0596\u05d5\u05bc","and Be astounded"],["t\u0259\u00b7m\u0101\u00b7h\u016b;","\u05ea\u05b0\u05bc\u05de\u05b8\u0591\u05d4\u05d5\u05bc","utterly"],["","!",""],["k\u00ee-","\u05db\u05b4\u05bc\u05d9\u05be","for"],["p\u0304\u014d\u00b7\u2018al","\u05e4\u05b9\u0599\u05e2\u05b7\u05dc\u0599","[I will] work"],["p\u014d\u00b7\u2018\u00eal","\u05e4\u05b9\u05bc\u05e2\u05b5\u05a3\u05dc","a work"],["b\u00ee\u00b7m\u00ea\u00b7\u1e35em,","\u05d1\u05b4\u05bc\u05bd\u05d9\u05de\u05b5\u05d9\u05db\u05b6\u0594\u05dd","in your days"],["",",",""],["l\u014d","\u05dc\u05b9\u05a5\u05d0","not"],["\u1e6fa\u00b7\u2019\u0103\u00b7m\u00ee\u00b7n\u016b","\u05ea\u05b7\u05d0\u05b2\u05de\u05b4\u0596\u05d9\u05e0\u05d5\u05bc","[Which] you would believe"],["",",",""],["k\u00ee","\u05db\u05b4\u05bc\u05a5\u05d9","though"],["y\u0259\u00b7sup\u00b7p\u0101r.","\u05d9\u05b0\u05e1\u05bb\u05e4\u05b8\u05bc\u05bd\u05e8\u05c3","it were told [you]"],["",".",""]],"The Lord's Answer"],"6":[[["k\u00ee-","\u05db\u05b4\u05bc\u05bd\u05d9\u05be","For"],["",",",""],["hin\u00b7n\u00ee","\u05d4\u05b4\u05e0\u05b0\u05e0\u05b4\u05a4\u05d9","indeed I"],["m\u00ea\u00b7q\u00eem","\u05de\u05b5\u05e7\u05b4\u05d9\u05dd\u0599","am raising up"],["\u2019e\u1e6f-","\u05d0\u05b6\u05ea\u05be",""],["hak\u00b7ka\u015b\u00b7d\u00eem,","\u05d4\u05b7\u05db\u05b7\u05bc\u05e9\u05b0\u05c2\u05d3\u05b4\u05bc\u0594\u05d9\u05dd","the Chaldeans"],["",",",""],["hag\u00b7g\u014d\u00b7w","\u05d4\u05b7\u05d2\u05bc\u0596\u05d5\u05b9\u05d9","a nation"],["",",",""],["ham\u00b7mar","\u05d4\u05b7\u05de\u05b7\u05bc\u05a3\u05e8","bitter"],["w\u0259\u00b7han\u00b7nim\u00b7h\u0101r;","\u05d5\u05b0\u05d4\u05b7\u05e0\u05b4\u05bc\u05de\u05b0\u05d4\u05b8\u0591\u05e8","and hasty"],["ha\u00b7h\u014d\u00b7w\u00b7l\u00ea\u1e35","\u05d4\u05b7\u05bd\u05d4\u05d5\u05b9\u05dc\u05b5\u05da\u05b0\u0599","which marches"],["l\u0259\u00b7mer\u00b7\u1e25\u0103\u00b7\u1e07\u00ea-","\u05dc\u05b0\u05de\u05b6\u05e8\u05b0\u05d7\u05b2\u05d1\u05b5\u05d9\u05be","through the breadth"],["\u2019e\u00b7re\u1e63,","\u05d0\u05b6\u0594\u05e8\u05b6\u05e5","of the earth"],["",",",""],["l\u0101\u00b7re\u00b7\u0161e\u1e6f","\u05dc\u05b8\u05e8\u05b6\u0596\u05e9\u05b6\u05c1\u05ea","to possess"],["mi\u0161\u00b7k\u0101\u00b7n\u014d\u00b7w\u1e6f","\u05de\u05b4\u05e9\u05b0\u05c1\u05db\u05b8\u05bc\u05e0\u05a5\u05d5\u05b9\u05ea","dwelling places"],["l\u014d-","\u05dc\u05b9\u05bc\u05d0\u05be","not"],["l\u014dw.","\u05dc\u05bd\u05d5\u05b9\u05c3","[that are] theirs"],["",".",""]],"The Lord's Answer"],"7":[[["\u2019\u0101\u00b7y\u014dm","\u05d0\u05b8\u05d9\u05b9\u05a5\u05dd","Awesome"],["w\u0259\u00b7n\u014d\u00b7w\u00b7r\u0101","\u05d5\u05b0\u05e0\u05d5\u05b9\u05e8\u05b8\u0596\u05d0","and dreadful"],["","-",""],["h\u016b;","\u05d4\u0591\u05d5\u05bc\u05d0","He [is]"],["mim\u00b7men\u00b7n\u016b","\u05de\u05b4\u05de\u05b6\u05bc\u0595\u05e0\u05bc\u05d5\u05bc","from himself"],["mi\u0161\u00b7p\u0101\u00b7\u1e6d\u014dw","\u05de\u05b4\u05e9\u05b0\u05c1\u05e4\u05b8\u05bc\u05d8\u05a5\u05d5\u05b9","His judgment"],["\u016b\u00b7\u015b\u0259\u00b7\u2019\u00ea\u00b7\u1e6f\u014dw","\u05d5\u05bc\u05e9\u05b0\u05c2\u05d0\u05b5\u05ea\u0596\u05d5\u05b9","and his dignity"],["y\u00ea\u00b7\u1e63\u00ea.","\u05d9\u05b5\u05e6\u05b5\u05bd\u05d0\u05c3","proceed"],["",".",""]],"The Lord's Answer"],"8":[[["w\u0259\u00b7qal\u00b7l\u016b","\u05d5\u05b0\u05e7\u05b7\u05dc\u05bc\u05a8\u05d5\u05bc","And are swifter"],["min\u00b7n\u0259\u00b7m\u00ea\u00b7r\u00eem","\u05de\u05b4\u05e0\u05b0\u05bc\u05de\u05b5\u05e8\u05b4\u059c\u05d9\u05dd","than leopards"],["",",",""],["s\u016b\u00b7s\u0101w,","\u05e1\u05d5\u05bc\u05e1\u05b8\u0597\u05d9\u05d5","their horses"],["w\u0259\u00b7\u1e25ad\u00b7d\u016b","\u05d5\u05b0\u05d7\u05b7\u05d3\u05bc\u05d5\u05bc\u0599","and more fierce"],["miz\u00b7z\u0259\u00b7\u2019\u00ea\u00b7\u1e07\u00ea","\u05de\u05b4\u05d6\u05b0\u05bc\u05d0\u05b5\u05a3\u05d1\u05b5\u05d9","than wolves"],["","-",""],["\u2018e\u00b7re\u1e07,","\u05e2\u05b6\u0594\u05e8\u05b6\u05d1","evening"],["\u016b\u00b7p\u0304\u0101\u00b7\u0161\u016b","\u05d5\u05bc\u05e4\u05b8\u0596\u05e9\u05c1\u05d5\u05bc","and charge ahead"],["p\u0101\u00b7r\u0101\u00b7\u0161\u0101w;","\u05e4\u05b8\u05bc\u05bd\u05e8\u05b8\u05e9\u05b8\u05c1\u0591\u05d9\u05d5","their chargers"],["\u016b\u00b7p\u0304\u0101\u00b7r\u0101\u00b7\u0161\u0101w","\u05d5\u05bc\u05e4\u05b8\u05bd\u05e8\u05b8\u05e9\u05b8\u05c1\u05d9\u05d5\u0599","and their cavalry"],["m\u00ea\u00b7r\u0101\u00b7\u1e25\u014d\u00b7wq","\u05de\u05b5\u05e8\u05b8\u05d7\u05a3\u05d5\u05b9\u05e7","from afar"],["","-",""],["y\u0101\u00b7\u1e07\u014d\u00b7\u2019\u016b,","\u05d9\u05b8\u05d1\u05b9\u0594\u05d0\u05d5\u05bc","comes"],["y\u0101\u00b7\u2018u\u00b7p\u0304\u016b","\u05d9\u05b8\u05e2\u05bb\u0595\u05e4\u05d5\u05bc","they fly"],["k\u0259\u00b7ne\u00b7\u0161er","\u05db\u05b0\u05bc\u05e0\u05b6\u0596\u05e9\u05b6\u05c1\u05e8","as the vulture"],["\u1e25\u0101\u0161","\u05d7\u05b8\u05a5\u05e9\u05c1","[that] hastens"],["le\u00b7\u2019\u0115\u00b7\u1e35\u014d\u00b7wl.","\u05dc\u05b6\u05d0\u05b1\u05db\u05bd\u05d5\u05b9\u05dc\u05c3","to eat"],["",".",""]],"The Lord's Answer"],"9":[[["kul\u00b7l\u014dh","\u05db\u05bb\u05bc\u05dc\u05b9\u05bc\u05d4\u0599","They all"],["l\u0259\u00b7\u1e25\u0101\u00b7m\u0101s","\u05dc\u05b0\u05d7\u05b8\u05de\u05b8\u05a3\u05e1","for violence"],["",".",""],["y\u0101\u00b7\u1e07\u014d\u00b7w,","\u05d9\u05b8\u05d1\u0594\u05d5\u05b9\u05d0","Come"],["m\u0259\u00b7\u1e21am\u00b7ma\u1e6f","\u05de\u05b0\u05d2\u05b7\u05de\u05b7\u05bc\u05a5\u05ea","are set"],["p\u0259\u00b7n\u00ea\u00b7hem","\u05e4\u05b0\u05bc\u05e0\u05b5\u05d9\u05d4\u05b6\u0596\u05dd","their faces"],["q\u0101\u00b7\u1e0f\u00ee\u00b7m\u0101h;","\u05e7\u05b8\u05d3\u05b4\u0591\u05d9\u05de\u05b8\u05d4","[like] the east [wind]"],["",",",""],["way\u00b7ye\u00b7\u2019\u0115\u00b7s\u014dp\u0304","\u05d5\u05b7\u05d9\u05b6\u05bc\u05d0\u05b1\u05e1\u05b9\u05a5\u05e3","and they gather"],["ka\u00b7\u1e25\u014d\u00b7wl","\u05db\u05b7\u05bc\u05d7\u0596\u05d5\u05b9\u05dc","like sand"],["\u0161e\u00b7\u1e07\u00ee.","\u05e9\u05b6\u05bd\u05c1\u05d1\u05b4\u05d9\u05c3","captives"],["",".",""]],"The Lord's Answer"],"10":[[["w\u0259\u00b7h\u016b","\u05d5\u05b0\u05d4\u05d5\u05bc\u05d0\u0599","And He"],["bam\u00b7m\u0259\u00b7l\u0101\u00b7\u1e35\u00eem","\u05d1\u05b7\u05bc\u05de\u05b0\u05bc\u05dc\u05b8\u05db\u05b4\u05a3\u05d9\u05dd","at kings"],["",",",""],["yi\u1e6f\u00b7qal\u00b7l\u0101s,","\u05d9\u05b4\u05ea\u05b0\u05e7\u05b7\u05dc\u05b8\u05bc\u0594\u05e1","scoffs"],["w\u0259\u00b7r\u014d\u00b7z\u0259\u00b7n\u00eem","\u05d5\u05b0\u05e8\u05b9\u05d6\u05b0\u05e0\u05b4\u0596\u05d9\u05dd","and princes"],["mi\u015b\u00b7\u1e25\u0101q","\u05de\u05b4\u05e9\u05b0\u05c2\u05d7\u05b8\u05a3\u05e7","are scorned"],["l\u014dw;","\u05dc\u0591\u05d5\u05b9","by him"],["h\u016b","\u05d4\u059a\u05d5\u05bc\u05d0","He"],["l\u0259\u00b7\u1e35\u0101l","\u05dc\u05b0\u05db\u05b8\u05dc\u05be","every"],["mi\u1e07\u00b7\u1e63\u0101r","\u05de\u05b4\u05d1\u05b0\u05e6\u05b8\u05a3\u05e8","stronghold"],["","-",""],["yi\u015b\u00b7\u1e25\u0101q,","\u05d9\u05b4\u05e9\u05b0\u05c2\u05d7\u05b8\u0594\u05e7","derides"],["way\u00b7yi\u1e63\u00b7b\u014dr","\u05d5\u05b7\u05d9\u05b4\u05bc\u05e6\u05b0\u05d1\u05b9\u05bc\u05a5\u05e8","for he heaps up"],["\u2018\u0101\u00b7p\u0304\u0101r","\u05e2\u05b8\u05e4\u05b8\u0596\u05e8","earthen [mounds]"],["",",",""],["way\u00b7yil\u00b7k\u0259\u00b7\u1e0f\u0101h.","\u05d5\u05b7\u05bd\u05d9\u05b4\u05bc\u05dc\u05b0\u05db\u05b0\u05bc\u05d3\u05b8\u05bd\u05d4\u05bc\u05c3","and seize it"],["",".",""]],"The Lord's Answer"],"11":[[["\u2019\u0101z","\u05d0\u05b8\u05a3\u05d6","Then"],["\u1e25\u0101\u00b7lap\u0304","\u05d7\u05b8\u05dc\u05b7\u05a5\u05e3","changes"],["",",",""],["r\u016b\u00b7a\u1e25","\u05e8\u059b\u05d5\u05bc\u05d7\u05b7","[his] mind"],["way\u00b7ya\u00b7\u2018\u0103\u00b7\u1e07\u014dr","\u05d5\u05b7\u05bd\u05d9\u05b7\u05bc\u05e2\u05b2\u05d1\u05b9\u0596\u05e8","and he transgresses"],["",",",""],["w\u0259\u00b7\u2019\u0101\u00b7\u0161\u00eam;","\u05d5\u05b0\u05d0\u05b8\u05e9\u05b5\u05c1\u0591\u05dd","and He commits offense"],["",",",""],["z\u016b","\u05d6\u05a5\u05d5\u05bc","[Ascribing] this"],["\u1e35\u014d\u00b7\u1e25\u014dw","\u05db\u05b9\u05d7\u0596\u05d5\u05b9","power"],["l\u00ea\u00b7l\u014d\u00b7h\u014dw.","\u05dc\u05b5\u05d0\u05dc\u05b9\u05d4\u05bd\u05d5\u05b9\u05c3","to his god"],["",".",""]],"Habakkuk's Second Complaint",null,"Psalm 11:1-7"],"12":[[["h\u0103\u00b7l\u014d\u00b7w","\u05d4\u05b2\u05dc\u05a7\u05d5\u05b9\u05d0","Are not"],["\u2019at\u00b7t\u0101h","\u05d0\u05b7\u05ea\u05b8\u05bc\u05a3\u05d4","You"],["miq\u00b7qe\u00b7\u1e0fem,","\u05de\u05b4\u05e7\u05b6\u05bc\u0597\u05d3\u05b6\u05dd","from everlasting"],["",",",""],["Yah\u00b7weh","\u05d9\u05b0\u05d4\u05d5\u05b8\u05a7\u05d4","Yahweh"],["\u2019\u0115\u00b7l\u014d\u00b7hay","\u05d0\u05b1\u05dc\u05b9\u05d4\u05b7\u059b\u05d9","my God"],["",",",""],["q\u0259\u00b7\u1e0f\u014d\u00b7\u0161\u00ee","\u05e7\u05b0\u05d3\u05b9\u05e9\u05b4\u05c1\u0596\u05d9","my Holy one"],["","?",""],["l\u014d","\u05dc\u05b9\u05a3\u05d0","not"],["n\u0101\u00b7m\u016b\u1e6f;","\u05e0\u05b8\u05de\u0591\u05d5\u05bc\u05ea","we shall die"],["",".",""],["Yah\u00b7weh","\u05d9\u05b0\u05d4\u05d5\u05b8\u05d4\u0599","Yahweh"],["l\u0259\u00b7mi\u0161\u00b7p\u0101\u1e6d","\u05dc\u05b0\u05de\u05b4\u05e9\u05b0\u05c1\u05e4\u05b8\u05bc\u05a3\u05d8","for judgment"],["","-",""],["\u015bam\u00b7t\u014dw,","\u05e9\u05b7\u05c2\u05de\u05b0\u05ea\u05bc\u0594\u05d5\u05b9","You have appointed them"],["w\u0259\u00b7\u1e63\u016br","\u05d5\u05b0\u05e6\u0596\u05d5\u05bc\u05e8","and Rock"],["",",",""],["l\u0259\u00b7h\u014d\u00b7w\u00b7\u1e35\u00ee\u00b7a\u1e25","\u05dc\u05b0\u05d4\u05d5\u05b9\u05db\u05b4\u05a5\u05d9\u05d7\u05b7","for correction"],["y\u0259\u00b7sa\u1e0f\u00b7t\u014dw.","\u05d9\u05b0\u05e1\u05b7\u05d3\u05b0\u05ea\u05bc\u05bd\u05d5\u05b9\u05c3","You have marked them"],["",".",""]],"Habakkuk's Second Complaint",null,"Psalm 11:1-7"],"13":[[["\u1e6d\u0259\u00b7h\u014d\u00b7wr","\u05d8\u05b0\u05d4\u05a4\u05d5\u05b9\u05e8","[You are] of purer"],["\u2018\u00ea\u00b7na\u00b7yim","\u05e2\u05b5\u05d9\u05e0\u05b7\u0599\u05d9\u05b4\u05dd\u0599","eyes"],["m\u00ea\u00b7r\u0259\u00b7\u2019\u014d\u00b7w\u1e6f","\u05de\u05b5\u05e8\u05b0\u05d0\u05a3\u05d5\u05b9\u05ea","than to behold"],["r\u0101\u2018,","\u05e8\u05b8\u0594\u05e2","evil"],["",",",""],["w\u0259\u00b7hab\u00b7b\u00ee\u1e6d","\u05d5\u05b0\u05d4\u05b7\u05d1\u05b4\u05bc\u05a5\u05d9\u05d8","and look"],["\u2019el-","\u05d0\u05b6\u05dc\u05be","on"],["\u2018\u0101\u00b7m\u0101l","\u05e2\u05b8\u05de\u05b8\u0596\u05dc","wickedness"],["","-",""],["l\u014d","\u05dc\u05b9\u05a3\u05d0","not"],["\u1e6f\u016b\u00b7\u1e35\u0101l;","\u05ea\u05d5\u05bc\u05db\u05b8\u0591\u05dc","cannot"],["l\u0101m\u00b7m\u0101h","\u05dc\u05b8\u05a4\u05de\u05b8\u05bc\u05d4","why"],["\u1e6fab\u00b7b\u00ee\u1e6d","\u05ea\u05b7\u05d1\u05b4\u05bc\u05d9\u05d8\u0599","do You look"],["b\u014d\u00b7w\u1e21\u00b7\u1e0f\u00eem,","\u05d1\u05bc\u05bd\u05d5\u05b9\u05d2\u05b0\u05d3\u05b4\u0594\u05d9\u05dd","on those who deal treacherously"],["",",",""],["ta\u00b7\u1e25\u0103\u00b7r\u00ee\u0161","\u05ea\u05b7\u05bc\u05d7\u05b2\u05e8\u05b4\u0595\u05d9\u05e9\u05c1","[And] hold Your tongue"],["b\u0259\u00b7\u1e07al\u00b7la\u2018","\u05d1\u05b0\u05bc\u05d1\u05b7\u05dc\u05b7\u05bc\u05a5\u05e2","when devours"],["r\u0101\u00b7\u0161\u0101\u2018","\u05e8\u05b8\u05e9\u05b8\u05c1\u0596\u05e2","the wicked"],["\u1e63ad\u00b7d\u00eeq","\u05e6\u05b7\u05d3\u05b4\u05bc\u05a5\u05d9\u05e7","a [person] more righteous"],["mim\u00b7men\u00b7n\u016b.","\u05de\u05b4\u05de\u05b6\u05bc\u05bd\u05e0\u05bc\u05d5\u05bc\u05c3","than he"],["",".",""]],"Habakkuk's Second Complaint",null,"Psalm 11:1-7"],"14":[[["wat\u00b7ta\u00b7\u2018\u0103\u00b7\u015beh","\u05d5\u05b7\u05ea\u05b7\u05bc\u05e2\u05b2\u05e9\u05b6\u05c2\u05a5\u05d4","And [Why] do You make"],["\u2019\u0101\u00b7\u1e0f\u0101m","\u05d0\u05b8\u05d3\u05b8\u0596\u05dd","men"],["ki\u1e0f\u00b7\u1e21\u00ea","\u05db\u05b4\u05bc\u05d3\u05b0\u05d2\u05b5\u05a3\u05d9","like fish"],["hay\u00b7y\u0101m;","\u05d4\u05b7\u05d9\u05b8\u05bc\u0591\u05dd","of the sea"],["",",",""],["k\u0259\u00b7re\u00b7me\u015b","\u05db\u05b0\u05bc\u05e8\u05b6\u0596\u05de\u05b6\u05e9\u05c2","Like creeping things"],["",",",""],["l\u014d-","\u05dc\u05b9\u05d0\u05be","[that have] no"],["m\u014d\u00b7\u0161\u00eal","\u05de\u05b9\u05e9\u05b5\u05c1\u05a5\u05dc","ruler"],["b\u014dw.","\u05d1\u05bc\u05bd\u05d5\u05b9\u05c3","over them"],["",".",""]],"Habakkuk's Second Complaint",null,"Psalm 11:1-7"],"15":[[["kul\u00b7l\u014dh","\u05db\u05bb\u05bc\u05dc\u05b9\u05bc\u05d4\u0599","All of them"],["b\u0259\u00b7\u1e25ak\u00b7k\u0101h","\u05d1\u05b0\u05bc\u05d7\u05b7\u05db\u05b8\u05bc\u05a3\u05d4","with a hook"],["",",",""],["h\u00ea\u00b7\u2018\u0103\u00b7l\u0101h,","\u05d4\u05b5\u05bd\u05e2\u05b2\u05dc\u05b8\u0594\u05d4","they take up"],["y\u0259\u00b7\u1e21\u014d\u00b7r\u00ea\u00b7h\u016b","\u05d9\u05b0\u05d2\u05b9\u05e8\u05b5\u05a3\u05d4\u05d5\u05bc","they catch them"],["\u1e07\u0259\u00b7\u1e25er\u00b7m\u014dw,","\u05d1\u05b0\u05d7\u05b6\u05e8\u05b0\u05de\u0594\u05d5\u05b9","in their net"],["",",",""],["w\u0259\u00b7ya\u00b7\u2019as\u00b7p\u0304\u00ea\u00b7h\u016b","\u05d5\u05b0\u05d9\u05b7\u05d0\u05b7\u05e1\u05b0\u05e4\u05b5\u0596\u05d4\u05d5\u05bc","and gather them"],["b\u0259\u00b7mi\u1e35\u00b7mar\u00b7t\u014dw;","\u05d1\u05b0\u05bc\u05de\u05b4\u05db\u05b0\u05de\u05b7\u05e8\u05b0\u05ea\u05bc\u0591\u05d5\u05b9","in their dragnet"],["","-",""],["\u2018al-","\u05e2\u05b7\u05dc\u05be","upon"],["k\u00ean","\u05db\u05b5\u05bc\u0596\u05df","thus"],["yi\u015b\u00b7ma\u1e25","\u05d9\u05b4\u05e9\u05b0\u05c2\u05de\u05b7\u05a5\u05d7","they rejoice"],["w\u0259\u00b7y\u0101\u00b7\u1e21\u00eel.","\u05d5\u05b0\u05d9\u05b8\u05d2\u05b4\u05bd\u05d9\u05dc\u05c3","and are glad"],["",".",""]],"Habakkuk's Second Complaint",null,"Psalm 11:1-7"],"16":[[["\u2018al-","\u05e2\u05b7\u05dc\u05be","Upon"],["k\u00ean","\u05db\u05b5\u05bc\u05df\u0599","thus"],["y\u0259\u00b7zab\u00b7b\u00ea\u00b7a\u1e25","\u05d9\u05b0\u05d6\u05b7\u05d1\u05b5\u05bc\u05a3\u05d7\u05b7","they sacrifice"],["l\u0259\u00b7\u1e25er\u00b7m\u014dw,","\u05dc\u05b0\u05d7\u05b6\u05e8\u05b0\u05de\u0594\u05d5\u05b9","to their net"],["",",",""],["w\u00ee\u00b7qa\u1e6d\u00b7\u1e6d\u00ear","\u05d5\u05b4\u05bd\u05d9\u05e7\u05b7\u05d8\u05b5\u05bc\u0596\u05e8","and burn incense"],["l\u0259\u00b7mi\u1e35\u00b7mar\u00b7t\u014dw;","\u05dc\u05b0\u05de\u05b4\u05db\u05b0\u05de\u05b7\u05e8\u05b0\u05ea\u05bc\u0591\u05d5\u05b9","to their dragnet"],["","-",""],["k\u00ee","\u05db\u05b4\u05bc\u05a4\u05d9","because"],["\u1e07\u0101\u00b7h\u00eam\u00b7m\u0101h","\u05d1\u05b8\u05d4\u05b5\u0599\u05de\u05b8\u05bc\u05d4\u0599","by them"],["\u0161\u0101\u00b7m\u00ean","\u05e9\u05b8\u05c1\u05de\u05b5\u05a3\u05df","sumptuous"],["",",",""],["\u1e25el\u00b7q\u014dw,","\u05d7\u05b6\u05dc\u05b0\u05e7\u0594\u05d5\u05b9","their share [is]"],["\u016b\u00b7ma\u00b7\u2019\u0103\u00b7\u1e35\u0101\u00b7l\u014dw","\u05d5\u05bc\u05de\u05b7\u05d0\u05b2\u05db\u05b8\u05dc\u0596\u05d5\u05b9","and their food"],["b\u0259\u00b7ri\u00b7\u2019\u0101h.","\u05d1\u05b0\u05bc\u05e8\u05b4\u05d0\u05b8\u05bd\u05d4\u05c3","fat"],["",".",""]],"Habakkuk's Second Complaint",null,"Psalm 11:1-7"],"17":[[["ha\u00b7\u2018al","\u05d4\u05b7\u05a5\u05e2\u05b7\u05dc","Shall"],["k\u00ean","\u05db\u05b5\u05bc\u0596\u05df","therefore"],["y\u0101\u00b7r\u00eeq","\u05d9\u05b8\u05e8\u05b4\u05a3\u05d9\u05e7","they empty"],["\u1e25er\u00b7m\u014dw;","\u05d7\u05b6\u05e8\u05b0\u05de\u0591\u05d5\u05b9","their net"],["",",",""],["w\u0259\u00b7\u1e6f\u0101\u00b7m\u00ee\u1e0f","\u05d5\u05b0\u05ea\u05b8\u05de\u05b4\u059b\u05d9\u05d3","and continue"],["la\u00b7h\u0103\u00b7r\u014d\u1e21","\u05dc\u05b7\u05d4\u05b2\u05e8\u05b9\u05a5\u05d2","to slay"],["g\u014d\u00b7w\u00b7yim","\u05d2\u05bc\u05d5\u05b9\u05d9\u05b4\u0596\u05dd","nations"],["","?",""],["l\u014d","\u05dc\u05b9\u05a5\u05d0","without"],["ya\u1e25\u00b7m\u014d\u00b7wl.","\u05d9\u05b7\u05d7\u05b0\u05de\u05bd\u05d5\u05b9\u05dc\u05c3","pity"],["",".",""],["s","\u05e1",""]],"Habakkuk's Second Complaint",null,"Psalm 11:1-7"]},"2":{"1":[[["\u2018al-","\u05e2\u05b7\u05dc\u05be","On"],["mi\u0161\u00b7mar\u00b7t\u00ee","\u05de\u05b4\u05e9\u05b0\u05c1\u05de\u05b7\u05e8\u05b0\u05ea\u05b4\u05bc\u05a3\u05d9","my watch"],["",",",""],["\u2019e\u00b7\u2018\u0115\u00b7m\u014d\u00b7\u1e0f\u0101h,","\u05d0\u05b6\u05e2\u05b1\u05de\u05b9\u0594\u05d3\u05b8\u05d4","I will stand"],["w\u0259\u00b7\u2019e\u1e6f\u00b7ya\u1e63\u00b7\u1e63\u0259\u00b7\u1e07\u0101h","\u05d5\u05b0\u05d0\u05b6\u05bd\u05ea\u05b0\u05d9\u05b7\u05e6\u05b0\u05bc\u05d1\u05b8\u0596\u05d4","and set myself"],["\u2018al-","\u05e2\u05b7\u05dc\u05be","on"],["m\u0101\u00b7\u1e63\u014d\u00b7wr;","\u05de\u05b8\u05e6\u0591\u05d5\u05b9\u05e8","the rampart"],["",",",""],["wa\u00b7\u2019\u0103\u00b7\u1e63ap\u00b7peh,","\u05d5\u05b7\u05d0\u05b2\u05e6\u05b7\u05e4\u05b6\u05bc\u0597\u05d4","and watch"],["lir\u00b7\u2019\u014d\u00b7w\u1e6f","\u05dc\u05b4\u05e8\u05b0\u05d0\u05d5\u05b9\u05ea\u0599","to see"],["mah-","\u05de\u05b7\u05d4\u05be","what"],["y\u0259\u00b7\u1e0fab\u00b7ber-","\u05d9\u05b0\u05d3\u05b7\u05d1\u05b6\u05bc\u05e8\u05be","He will say"],["b\u00ee,","\u05d1\u05b4\u05bc\u0594\u05d9","to me"],["\u016b\u00b7m\u0101h","\u05d5\u05bc\u05de\u05b8\u05a5\u05d4","and what"],["\u2019\u0101\u00b7\u0161\u00ee\u1e07","\u05d0\u05b8\u05e9\u05b4\u05c1\u0596\u05d9\u05d1","I will answer"],["\u2018al-","\u05e2\u05b7\u05dc\u05be","when"],["t\u014d\u00b7w\u00b7\u1e35a\u1e25\u00b7t\u00ee.","\u05ea\u05bc\u05d5\u05b9\u05db\u05b7\u05d7\u05b0\u05ea\u05b4\u05bc\u05bd\u05d9\u05c3","I am corrected"],["",".",""]],"The Lord Answers Again"],"2":[[["way\u00b7ya\u00b7\u2018\u0103\u00b7n\u00ea\u00b7n\u00ee","\u05d5\u05b7\u05d9\u05b7\u05bc\u05e2\u05b2\u05e0\u05b5\u05a4\u05e0\u05b4\u05d9","And answered me"],["Yah\u00b7weh","\u05d9\u05b0\u05d4\u05d5\u05b8\u05d4\u0599","Yahweh"],["way\u00b7y\u014d\u00b7mer,","\u05d5\u05b7\u05d9\u05b9\u05bc\u0594\u05d0\u05de\u05b6\u05e8","and said"],["",",",""],["k\u0259\u00b7\u1e6f\u014d\u00b7w\u1e07","\u05db\u05b0\u05bc\u05ea\u05a3\u05d5\u05b9\u05d1","Write"],["\u1e25\u0101\u00b7z\u014d\u00b7wn,","\u05d7\u05b8\u05d6\u0594\u05d5\u05b9\u05df","the vision"],["",",",""],["\u016b\u00b7\u1e07\u0101\u00b7\u2019\u00ear","\u05d5\u05bc\u05d1\u05b8\u05d0\u05b5\u0596\u05e8","and make [it] plain"],["\u2018al-","\u05e2\u05b7\u05dc\u05be","on"],["hal\u00b7lu\u00b7\u1e25\u014d\u00b7w\u1e6f;","\u05d4\u05b7\u05dc\u05bb\u05bc\u05d7\u0591\u05d5\u05b9\u05ea","tablets"],["",",",""],["l\u0259\u00b7ma\u00b7\u2018an","\u05dc\u05b0\u05de\u05b7\u05a5\u05e2\u05b7\u05df","that"],["y\u0101\u00b7r\u016b\u1e63","\u05d9\u05b8\u05e8\u0596\u05d5\u05bc\u05e5","he may run"],["q\u014d\u00b7w\u00b7r\u00ea","\u05e7\u05a5\u05d5\u05b9\u05e8\u05b5\u05d0","who reads"],["\u1e07\u014dw.","\u05d1\u05bd\u05d5\u05b9\u05c3","it"],["",".",""]],"The Lord Answers Again"],"3":[[["k\u00ee","\u05db\u05b4\u05bc\u05a3\u05d9","For"],["\u2018\u014d\u00b7w\u1e0f","\u05e2\u05a4\u05d5\u05b9\u05d3","yet"],["\u1e25\u0101\u00b7z\u014d\u00b7wn","\u05d7\u05b8\u05d6\u05d5\u05b9\u05df\u0599","the vision [is]"],["lam\u00b7m\u014d\u00b7w\u00b7\u2018\u00ea\u1e0f,","\u05dc\u05b7\u05de\u05bc\u05d5\u05b9\u05e2\u05b5\u0594\u05d3","for an appointed time"],["",",",""],["w\u0259\u00b7y\u0101\u00b7p\u0304\u00ea\u00b7a\u1e25","\u05d5\u05b0\u05d9\u05b8\u05e4\u05b5\u05a5\u05d7\u05b7","but it will speak"],["",",",""],["laq\u00b7q\u00ea\u1e63","\u05dc\u05b7\u05e7\u05b5\u05bc\u0596\u05e5","at the end"],["w\u0259\u00b7l\u014d","\u05d5\u05b0\u05dc\u05b9\u05a3\u05d0","and not"],["y\u0259\u00b7\u1e35az\u00b7z\u00ea\u1e07;","\u05d9\u05b0\u05db\u05b7\u05d6\u05b5\u05bc\u0591\u05d1","it will lie"],["",".",""],["\u2019im-","\u05d0\u05b4\u05dd\u05be","Though"],["yi\u1e6f\u00b7mah\u00b7m\u0101h","\u05d9\u05b4\u05ea\u05b0\u05de\u05b7\u05d4\u05b0\u05de\u05b8\u05d4\u05bc\u0599","it tarries"],["",",",""],["\u1e25ak\u00b7k\u00eah-","\u05d7\u05b7\u05db\u05b5\u05bc\u05d4\u05be","wait"],["l\u014dw,","\u05dc\u0594\u05d5\u05b9","for it"],["k\u00ee-","\u05db\u05b4\u05bc\u05bd\u05d9\u05be","because"],["\u1e07\u014d","\u05d1\u05b9\u05a5\u05d0","surely"],["y\u0101\u00b7\u1e07\u014d","\u05d9\u05b8\u05d1\u05b9\u0596\u05d0","it will come"],["",",",""],["l\u014d","\u05dc\u05b9\u05a5\u05d0","not"],["y\u0259\u00b7\u2019a\u00b7\u1e25\u00ear.","\u05d9\u05b0\u05d0\u05b7\u05d7\u05b5\u05bd\u05e8\u05c3","it will tarry"],["",".",""]],"The Lord Answers Again"],"4":[[["hin\u00b7n\u00eah","\u05d4\u05b4\u05e0\u05b5\u05bc\u05a3\u05d4","Behold"],["",",",""],["\u2018up\u00b7p\u0259\u00b7l\u0101h,","\u05e2\u05bb\u05e4\u05b0\u05bc\u05dc\u05b8\u0594\u05d4","the proud"],["l\u014d-","\u05dc\u05b9\u05d0\u05be","not"],["y\u0101\u00b7\u0161\u0259\u00b7r\u0101h","\u05d9\u05b8\u05e9\u05b0\u05c1\u05e8\u05b8\u05a5\u05d4","is upright"],["nap\u0304\u00b7\u0161\u014dw","\u05e0\u05b7\u05e4\u05b0\u05e9\u05c1\u0596\u05d5\u05b9","His soul"],["b\u014dw;","\u05d1\u05bc\u0591\u05d5\u05b9","in him"],["w\u0259\u00b7\u1e63ad\u00b7d\u00eeq","\u05d5\u05b0\u05e6\u05b7\u05d3\u05b4\u05bc\u0596\u05d9\u05e7","but the just"],["be\u00b7\u2019\u0115\u00b7m\u016b\u00b7n\u0101\u00b7\u1e6f\u014dw","\u05d1\u05b6\u05bc\u05d0\u05b1\u05de\u05d5\u05bc\u05e0\u05b8\u05ea\u05a5\u05d5\u05b9","by his faith"],["yi\u1e25\u00b7yeh.","\u05d9\u05b4\u05d7\u05b0\u05d9\u05b6\u05bd\u05d4\u05c3","shall live"],["",".",""]],"The Lord Answers Again"],"5":[[["w\u0259\u00b7\u2019ap\u0304","\u05d5\u05b0\u05d0\u05b7\u05e3\u0599","And indeed"],["k\u00ee-","\u05db\u05b4\u05bc\u05bd\u05d9\u05be","because"],["hay\u00b7ya\u00b7yin","\u05d4\u05b7\u05d9\u05b7\u05bc\u05a3\u05d9\u05b4\u05df","by wine"],["",",",""],["b\u014d\u00b7w\u00b7\u1e21\u00ea\u1e0f,","\u05d1\u05bc\u05d5\u05b9\u05d2\u05b5\u0594\u05d3","he transgresses"],["ge\u00b7\u1e07er","\u05d2\u05b6\u05bc\u05a5\u05d1\u05b6\u05e8","[He is] a man"],["",",",""],["y\u0101\u00b7h\u00eer","\u05d9\u05b8\u05d4\u05b4\u0596\u05d9\u05e8","proud"],["w\u0259\u00b7l\u014d","\u05d5\u05b0\u05dc\u05b9\u05a3\u05d0","and not"],["yin\u00b7weh;","\u05d9\u05b4\u05e0\u05b0\u05d5\u05b6\u0591\u05d4","he does stay at home"],["",",",""],["\u2019\u0103\u00b7\u0161er","\u05d0\u05b2\u05e9\u05b6\u05c1\u05e8\u05a9","because"],["hir\u00b7\u1e25\u00ee\u1e07","\u05d4\u05b4\u05e8\u05b0\u05d7\u05b4\u05a8\u05d9\u05d1","he enlarges"],["ki\u0161\u00b7\u2019\u014d\u00b7wl","\u05db\u05b4\u05bc\u05e9\u05b0\u05c1\u05d0\u059c\u05d5\u05b9\u05dc","as hell"],["",",",""],["nap\u0304\u00b7\u0161\u014dw,","\u05e0\u05b7\u05e4\u05b0\u05e9\u05c1\u0597\u05d5\u05b9","his desire"],["w\u0259\u00b7h\u016b","\u05d5\u05b0\u05d4\u05a4\u05d5\u05bc\u05d0","and he [is]"],["\u1e35am\u00b7m\u0101\u00b7we\u1e6f","\u05db\u05b7\u05de\u05b8\u05bc\u0599\u05d5\u05b6\u05ea\u0599","like death"],["",",",""],["w\u0259\u00b7l\u014d","\u05d5\u05b0\u05dc\u05b9\u05a3\u05d0","and cannot"],["yi\u015b\u00b7b\u0101\u2018,","\u05d9\u05b4\u05e9\u05b0\u05c2\u05d1\u05b8\u05bc\u0594\u05e2","be satisfied"],["",",",""],["way\u00b7ye\u00b7\u2019\u0115\u00b7s\u014dp\u0304","\u05d5\u05b7\u05d9\u05b6\u05bc\u05d0\u05b1\u05e1\u05b9\u05a4\u05e3","and He gathers"],["\u2019\u00ea\u00b7l\u0101w","\u05d0\u05b5\u05dc\u05b8\u05d9\u05d5\u0599","to himself"],["k\u0101l-","\u05db\u05b8\u05bc\u05dc\u05be","all"],["hag\u00b7g\u014d\u00b7w\u00b7yim,","\u05d4\u05b7\u05d2\u05bc\u05d5\u05b9\u05d9\u05b4\u0594\u05dd","nations"],["",",",""],["way\u00b7yiq\u00b7b\u014d\u1e63","\u05d5\u05b7\u05d9\u05b4\u05bc\u05e7\u05b0\u05d1\u05b9\u05bc\u05a5\u05e5","and heaps up"],["\u2019\u00ea\u00b7l\u0101w","\u05d0\u05b5\u05dc\u05b8\u0596\u05d9\u05d5","for himself"],["k\u0101l-","\u05db\u05b8\u05bc\u05dc\u05be","all"],["h\u0101\u00b7\u2018am\u00b7m\u00eem.","\u05d4\u05b8\u05e2\u05b7\u05de\u05b4\u05bc\u05bd\u05d9\u05dd\u05c3","peoples"],["",".",""]],"Woe to the Chaldeans"],"6":[[["h\u0103\u00b7l\u014d\u00b7w-","\u05d4\u05b2\u05dc\u05d5\u05b9\u05d0\u05be","Will not"],["\u2019\u00eal\u00b7leh","\u05d0\u05b5\u05a3\u05dc\u05b6\u05bc\u05d4","these"],["\u1e35ul\u00b7l\u0101m,","\u05db\u05bb\u05dc\u05b8\u05bc\u0597\u05dd","all"],["\u2018\u0101\u00b7l\u0101w","\u05e2\u05b8\u05dc\u05b8\u05d9\u05d5\u0599","against him"],["m\u0101\u00b7\u0161\u0101l","\u05de\u05b8\u05e9\u05b8\u05c1\u05a3\u05dc","a proverb"],["yi\u015b\u00b7\u015b\u0101\u00b7\u2019\u016b,","\u05d9\u05b4\u05e9\u05b8\u05bc\u05c2\u0594\u05d0\u05d5\u05bc","take up"],["\u016b\u00b7m\u0259\u00b7l\u00ee\u00b7\u1e63\u0101h","\u05d5\u05bc\u05de\u05b0\u05dc\u05b4\u05d9\u05e6\u05b8\u0596\u05d4","and taunting"],["\u1e25\u00ee\u00b7\u1e0f\u014d\u00b7w\u1e6f","\u05d7\u05b4\u05d9\u05d3\u05a3\u05d5\u05b9\u05ea","a riddle"],["l\u014dw;","\u05dc\u0591\u05d5\u05b9","against him"],["w\u0259\u00b7y\u014d\u00b7mar,","\u05d5\u05b0\u05d9\u05b9\u05d0\u05de\u05b7\u0597\u05e8","and say"],["",",",""],["h\u014d\u00b7w","\u05d4\u059a\u05d5\u05b9\u05d9","Woe"],["ham\u00b7mar\u00b7beh","\u05d4\u05b7\u05de\u05b7\u05bc\u05e8\u05b0\u05d1\u05b6\u05bc\u05a3\u05d4","to him who increases"],["l\u014d-","\u05dc\u05b9\u05bc\u05d0\u05be","not"],["l\u014dw,","\u05dc\u0594\u05d5\u05b9","[What] is his"],["\u2018a\u1e0f-","\u05e2\u05b7\u05d3\u05be","how"],["m\u0101\u00b7\u1e6fay","\u05de\u05b8\u05ea\u05b7\u0595\u05d9","long"],["\u016b\u00b7ma\u1e35\u00b7b\u00ee\u1e0f","\u05d5\u05bc\u05de\u05b7\u05db\u05b0\u05d1\u05b4\u05bc\u05a5\u05d9\u05d3","and who loads himself"],["\u2018\u0101\u00b7l\u0101w","\u05e2\u05b8\u05dc\u05b8\u0596\u05d9\u05d5","to him"],["\u2018a\u1e07\u00b7\u1e6d\u00ee\u1e6d.","\u05e2\u05b7\u05d1\u05b0\u05d8\u05b4\u05bd\u05d9\u05d8\u05c3","with many pledges"],["","!",""]],"Woe to the Chaldeans"],"7":[[["h\u0103\u00b7l\u014d\u00b7w","\u05d4\u05b2\u05dc\u05a3\u05d5\u05b9\u05d0","will not"],["p\u0304e\u00b7\u1e6fa\u2018,","\u05e4\u05b6\u0597\u05ea\u05b7\u05e2","suddenly"],["y\u0101\u00b7q\u016b\u00b7m\u016b","\u05d9\u05b8\u05e7\u0599\u05d5\u05bc\u05de\u05d5\u05bc\u0599","rise up"],["n\u014d\u00b7\u0161\u0259\u00b7\u1e35e\u00b7\u1e35\u0101,","\u05e0\u05b9\u05e9\u05b0\u05c1\u05db\u05b6\u0594\u05d9\u05da\u05b8","your creditors"],["w\u0259\u00b7yiq\u00b7\u1e63\u016b","\u05d5\u05b0\u05d9\u05b4\u05e7\u05b0\u05e6\u0596\u05d5\u05bc","and will they not awaken"],["m\u0259\u00b7za\u2018\u00b7z\u0259\u00b7\u2018e\u00b7\u1e35\u0101;","\u05de\u05b0\u05d6\u05b7\u05e2\u05b0\u05d6\u05b0\u05e2\u05b6\u0591\u05d9\u05da\u05b8","who oppress you"],["w\u0259\u00b7h\u0101\u00b7y\u00ee\u00b7\u1e6f\u0101","\u05d5\u05b0\u05d4\u05b8\u05d9\u05b4\u05a5\u05d9\u05ea\u05b8","and you will become"],["lim\u00b7\u0161is\u00b7s\u014d\u00b7w\u1e6f","\u05dc\u05b4\u05de\u05b0\u05e9\u05b4\u05c1\u05e1\u05bc\u0596\u05d5\u05b9\u05ea","booty"],["l\u0101\u00b7m\u014dw.","\u05dc\u05b8\u05bd\u05de\u05d5\u05b9\u05c3","their"],["",".",""]],"Woe to the Chaldeans"],"8":[[["k\u00ee","\u05db\u05b4\u05bc\u05bd\u05d9\u202a\u202c","Because"],["\u2019at\u00b7t\u0101h","\u05d0\u05b7\u05ea\u05b8\u05bc\u05a4\u05d4","you"],["\u0161al\u00b7l\u014d\u00b7w\u00b7\u1e6f\u0101","\u05e9\u05b7\u05c1\u05dc\u05bc\u0599\u05d5\u05b9\u05ea\u05b8\u0599","have plundered"],["g\u014d\u00b7w\u00b7yim","\u05d2\u05bc\u05d5\u05b9\u05d9\u05b4\u05a3\u05dd","nations"],["",",",""],["rab\u00b7b\u00eem,","\u05e8\u05b7\u05d1\u05b4\u05bc\u0594\u05d9\u05dd","many"],["y\u0259\u00b7\u0161\u0101l\u00b7l\u016b\u00b7\u1e35\u0101","\u05d9\u05b0\u05e9\u05b8\u05c1\u05dc\u05bc\u0596\u05d5\u05bc\u05da\u05b8","shall plunder you"],["k\u0101l-","\u05db\u05b8\u05bc\u05dc\u05be","all"],["ye\u00b7\u1e6fer","\u05d9\u05b6\u05a3\u05ea\u05b6\u05e8","the remnant"],["\u2018am\u00b7m\u00eem;","\u05e2\u05b7\u05de\u05b4\u05bc\u0591\u05d9\u05dd","of the people"],["mid\u00b7d\u0259\u00b7m\u00ea","\u05de\u05b4\u05d3\u05b0\u05bc\u05de\u05b5\u05a4\u05d9","because of blood"],["",",",""],["\u2019\u0101\u00b7\u1e0f\u0101m","\u05d0\u05b8\u05d3\u05b8\u05dd\u0599","of men"],["wa\u00b7\u1e25\u0103\u00b7mas-","\u05d5\u05b7\u05d7\u05b2\u05de\u05b7\u05e1\u05be","and the violence"],["\u2019e\u00b7re\u1e63,","\u05d0\u05b6\u0594\u05e8\u05b6\u05e5","of the land"],["",",",""],["qir\u00b7y\u0101h","\u05e7\u05b4\u05e8\u05b0\u05d9\u05b8\u0596\u05d4","[and] the city"],["",",",""],["w\u0259\u00b7\u1e35\u0101l","\u05d5\u05b0\u05db\u05b8\u05dc\u05be","and of all"],["y\u014d\u00b7\u0161\u0259\u00b7\u1e07\u00ea","\u05d9\u05b9\u05a5\u05e9\u05b0\u05c1\u05d1\u05b5\u05d9","who dwell"],["\u1e07\u0101h.","\u05d1\u05b8\u05bd\u05d4\u05bc\u05c3","in it"],["",".",""],["p\u0304","\u05e4",""]],"Woe to the Chaldeans"],"9":[[["h\u014d\u00b7w,","\u05d4\u0597\u05d5\u05b9\u05d9","Woe"],["b\u014d\u00b7\u1e63\u00ea\u00b7a\u2018","\u05d1\u05b9\u05bc\u05e6\u05b5\u059b\u05e2\u05b7","to him who covets"],["be\u00b7\u1e63a\u2018","\u05d1\u05b6\u05bc\u05a5\u05e6\u05b7\u05e2","gain"],["r\u0101\u2018","\u05e8\u05b8\u0596\u05e2","evil"],["l\u0259\u00b7\u1e07\u00ea\u00b7\u1e6f\u014dw;","\u05dc\u05b0\u05d1\u05b5\u05d9\u05ea\u0591\u05d5\u05b9","for his house"],["",",",""],["l\u0101\u00b7\u015b\u016bm","\u05dc\u05b8\u05e9\u05c2\u05a4\u05d5\u05bc\u05dd","that he may set"],["bam\u00b7m\u0101\u00b7r\u014d\u00b7wm","\u05d1\u05b7\u05bc\u05de\u05b8\u05bc\u05e8\u05d5\u05b9\u05dd\u0599","on high"],["",",",""],["qin\u00b7n\u014dw,","\u05e7\u05b4\u05e0\u05bc\u0594\u05d5\u05b9","his nest"],["l\u0259\u00b7hin\u00b7n\u0101\u00b7\u1e63\u00eal","\u05dc\u05b0\u05d4\u05b4\u05e0\u05b8\u05bc\u05e6\u05b5\u0596\u05dc","that he may be delivered"],["mik\u00b7kap\u0304-","\u05de\u05b4\u05db\u05b7\u05bc\u05e3\u05be","from the hand"],["r\u0101\u2018.","\u05e8\u05b8\u05bd\u05e2\u05c3","of disaster"],["","!",""]],"Woe to the Chaldeans"],"10":[[["y\u0101\u00b7\u2018a\u1e63\u00b7t\u0101","\u05d9\u05b8\u05e2\u05b7\u05a5\u05e6\u05b0\u05ea\u05b8\u05bc","You give counsel"],["b\u014d\u00b7\u0161e\u1e6f","\u05d1\u05b9\u05bc\u0596\u05e9\u05b6\u05c1\u05ea","shameful"],["l\u0259\u00b7\u1e07\u00ea\u00b7\u1e6fe\u00b7\u1e35\u0101;","\u05dc\u05b0\u05d1\u05b5\u05d9\u05ea\u05b6\u0591\u05da\u05b8","to your house"],["q\u0259\u00b7\u1e63\u014d\u00b7w\u1e6f-","\u05e7\u05b0\u05e6\u05d5\u05b9\u05ea\u05be","Cutting off"],["\u2018am\u00b7m\u00eem","\u05e2\u05b7\u05de\u05b4\u05bc\u05a5\u05d9\u05dd","peoples"],["",",",""],["rab\u00b7b\u00eem","\u05e8\u05b7\u05d1\u05b4\u05bc\u0596\u05d9\u05dd","many"],["w\u0259\u00b7\u1e25\u014d\u00b7w\u00b7\u1e6d\u00ea","\u05d5\u05b0\u05d7\u05d5\u05b9\u05d8\u05b5\u05a5\u05d0","and sin"],["nap\u0304\u00b7\u0161e\u00b7\u1e35\u0101.","\u05e0\u05b7\u05e4\u05b0\u05e9\u05b6\u05bd\u05c1\u05da\u05b8\u05c3","[against] your soul"],["",".",""]],"Woe to the Chaldeans"],"11":[[["k\u00ee-","\u05db\u05b4\u05bc\u05d9\u05be","For"],["\u2019e\u00b7\u1e07en","\u05d0\u05b6\u0596\u05d1\u05b6\u05df","the stone"],["miq\u00b7q\u00eer","\u05de\u05b4\u05e7\u05b4\u05bc\u05a3\u05d9\u05e8","from the wall"],["",",",""],["tiz\u00b7\u2018\u0101q;","\u05ea\u05b4\u05bc\u05d6\u05b0\u05e2\u05b8\u0591\u05e7","will cry out"],["w\u0259\u00b7\u1e35\u0101\u00b7p\u0304\u00ees","\u05d5\u05b0\u05db\u05b8\u05e4\u05b4\u0596\u05d9\u05e1","and the beam"],["m\u00ea\u00b7\u2018\u00ea\u1e63","\u05de\u05b5\u05e2\u05b5\u05a5\u05e5","from the timbers"],["ya\u00b7\u2018\u0103\u00b7nen\u00b7n\u0101h.","\u05d9\u05b7\u05e2\u05b2\u05e0\u05b6\u05bd\u05e0\u05b8\u05bc\u05d4\u05c3","will answer it"],["",".",""],["p\u0304","\u05e4",""]],"Woe to the Chaldeans"],"12":[[["h\u014d\u00b7w","\u05d4\u059b\u05d5\u05b9\u05d9","Woe"],["b\u014d\u00b7neh","\u05d1\u05b9\u05bc\u05e0\u05b6\u05a5\u05d4","to him who builds"],["\u2018\u00eer","\u05e2\u05b4\u0596\u05d9\u05e8","a town"],["b\u0259\u00b7\u1e0f\u0101\u00b7m\u00eem;","\u05d1\u05b0\u05bc\u05d3\u05b8\u05de\u05b4\u0591\u05d9\u05dd","with bloodshed"],["",",",""],["w\u0259\u00b7\u1e35\u014d\u00b7w\u00b7n\u00ean","\u05d5\u05b0\u05db\u05d5\u05b9\u05e0\u05b5\u05a5\u05df","and who establishes"],["qir\u00b7y\u0101h","\u05e7\u05b4\u05e8\u05b0\u05d9\u05b8\u0596\u05d4","a city"],["b\u0259\u00b7\u2018aw\u00b7l\u0101h.","\u05d1\u05b0\u05bc\u05e2\u05b7\u05d5\u05b0\u05dc\u05b8\u05bd\u05d4\u05c3","by iniquity"],["","!",""]],"Woe to the Chaldeans"],"13":[[["h\u0103\u00b7l\u014d\u00b7w","\u05d4\u05b2\u05dc\u05a3\u05d5\u05b9\u05d0","[is it] not"],["hin\u00b7n\u00eah,","\u05d4\u05b4\u05e0\u05b5\u05bc\u0594\u05d4","behold"],["",",",""],["m\u00ea\u00b7\u2019\u00ea\u1e6f","\u05de\u05b5\u05d0\u05b5\u0596\u05ea","of"],["Yah\u00b7weh","\u05d9\u05b0\u05d4\u05d5\u05b8\u05a3\u05d4","Yahweh"],["\u1e63\u0259\u00b7\u1e07\u0101\u00b7\u2019\u014d\u00b7w\u1e6f;","\u05e6\u05b0\u05d1\u05b8\u05d0\u0591\u05d5\u05b9\u05ea","of hosts"],["w\u0259\u00b7y\u00ee\u00b7\u1e21\u0259\u00b7\u2018\u016b","\u05d5\u05b0\u05d9\u05b4\u05bd\u05d9\u05d2\u05b0\u05e2\u05a4\u05d5\u05bc","that labor"],["\u2018am\u00b7m\u00eem","\u05e2\u05b7\u05de\u05b4\u05bc\u05d9\u05dd\u0599","the peoples"],["b\u0259\u00b7\u1e0f\u00ea-","\u05d1\u05b0\u05bc\u05d3\u05b5\u05d9\u05be","to feed"],["\u2019\u00ea\u0161,","\u05d0\u05b5\u0594\u05e9\u05c1","the fire"],["",",",""],["\u016b\u00b7l\u0259\u00b7\u2019um\u00b7m\u00eem","\u05d5\u05bc\u05dc\u05b0\u05d0\u05bb\u05de\u05b4\u05bc\u0596\u05d9\u05dd","and nations"],["b\u0259\u00b7\u1e0f\u00ea-","\u05d1\u05b0\u05bc\u05d3\u05b5\u05d9\u05be","in"],["r\u00eeq","\u05e8\u05b4\u05a5\u05d9\u05e7","vain"],["yi\u00b7\u2018\u0101\u00b7p\u0304\u016b.","\u05d9\u05b4\u05e2\u05b8\u05bd\u05e4\u05d5\u05bc\u05c3","weary themselves"],["","?",""]],"Woe to the Chaldeans"],"14":[[["k\u00ee","\u05db\u05b4\u05bc\u059a\u05d9","for"],["tim\u00b7m\u0101\u00b7l\u00ea","\u05ea\u05b4\u05bc\u05de\u05b8\u05bc\u05dc\u05b5\u05a3\u05d0","will be filled"],["h\u0101\u00b7\u2019\u0101\u00b7re\u1e63,","\u05d4\u05b8\u05d0\u05b8\u0594\u05e8\u05b6\u05e5","the earth"],["l\u0101\u00b7\u1e0fa\u00b7\u2018a\u1e6f","\u05dc\u05b8\u05d3\u05b7\u0596\u05e2\u05b7\u05ea","with the knowledge"],["\u2019e\u1e6f-","\u05d0\u05b6\u05ea\u05be","of"],["k\u0259\u00b7\u1e07\u014d\u00b7w\u1e0f","\u05db\u05b0\u05bc\u05d1\u05a3\u05d5\u05b9\u05d3","the glory"],["Yah\u00b7weh;","\u05d9\u05b0\u05d4\u05d5\u05b8\u0591\u05d4","of Yahweh"],["",",",""],["kam\u00b7ma\u00b7yim","\u05db\u05b7\u05bc\u05de\u05b7\u05bc\u0596\u05d9\u05b4\u05dd","as the waters"],["y\u0259\u00b7\u1e35as\u00b7s\u016b","\u05d9\u05b0\u05db\u05b7\u05e1\u05bc\u05a5\u05d5\u05bc","cover"],["\u2018al-","\u05e2\u05b7\u05dc\u05be","on"],["y\u0101m.","\u05d9\u05b8\u05bd\u05dd\u05c3","the sea"],["",".",""],["s","\u05e1",""]],"Woe to the Chaldeans"],"15":[[["h\u014d\u00b7w","\u05d4\u059a\u05d5\u05b9\u05d9","Woe"],["ma\u0161\u00b7q\u00eah","\u05de\u05b7\u05e9\u05b0\u05c1\u05e7\u05b5\u05a3\u05d4","to him who gives drink to"],["r\u00ea\u00b7\u2018\u00ea\u00b7h\u016b,","\u05e8\u05b5\u05e2\u05b5\u0594\u05d4\u05d5\u05bc","his neighbor"],["",",",""],["m\u0259\u00b7sap\u00b7p\u00ea\u00b7a\u1e25","\u05de\u05b0\u05e1\u05b7\u05e4\u05b5\u05bc\u05a5\u05d7\u05b7","Pressing [him to]"],["\u1e25\u0103\u00b7m\u0101\u00b7\u1e6f\u0259\u00b7\u1e35\u0101","\u05d7\u05b2\u05de\u05b8\u05ea\u05b0\u05da\u05b8\u0596","your bottle"],["w\u0259\u00b7\u2019ap\u0304","\u05d5\u05b0\u05d0\u05b7\u05a3\u05e3","and Even"],["",",",""],["\u0161ak\u00b7k\u00ear;","\u05e9\u05b7\u05c1\u05db\u05b5\u05bc\u0591\u05e8","to make [him] drunk"],["l\u0259\u00b7ma\u00b7\u2018an","\u05dc\u05b0\u05de\u05b7\u05a5\u05e2\u05b7\u05df","that"],["hab\u00b7b\u00ee\u1e6d","\u05d4\u05b7\u05d1\u05b4\u05bc\u0596\u05d9\u05d8","you may look"],["\u2018al-","\u05e2\u05b7\u05dc\u05be","on"],["m\u0259\u00b7\u2018\u014d\u00b7w\u00b7r\u00ea\u00b7hem.","\u05de\u05b0\u05e2\u05d5\u05b9\u05e8\u05b5\u05d9\u05d4\u05b6\u05bd\u05dd\u05c3","his nakedness"],["","!",""]],"Woe to the Chaldeans"],"16":[[["\u015b\u0101\u00b7\u1e07a\u2018\u00b7t\u0101","\u05e9\u05b8\u05c2\u05d1\u05b7\u05a4\u05e2\u05b0\u05ea\u05b8\u05bc","You are filled"],["q\u0101\u00b7l\u014d\u00b7wn","\u05e7\u05b8\u05dc\u05d5\u05b9\u05df\u0599","with shame"],["mik\u00b7k\u0101\u00b7\u1e07\u014d\u00b7w\u1e0f,","\u05de\u05b4\u05db\u05b8\u05bc\u05d1\u0594\u05d5\u05b9\u05d3","instead of glory"],["",".",""],["\u0161\u0259\u00b7\u1e6f\u00eah","\u05e9\u05b0\u05c1\u05ea\u05b5\u05a5\u05d4","Drink"],["\u1e21am-","\u05d2\u05b7\u05dd\u05be","also"],["",",",""],["\u2019at\u00b7t\u0101h","\u05d0\u05b7\u0596\u05ea\u05b8\u05bc\u05d4","You"],["w\u0259\u00b7h\u00ea\u00b7\u2018\u0101\u00b7r\u00eal;","\u05d5\u05b0\u05d4\u05b5\u05bd\u05e2\u05b8\u05e8\u05b5\u0591\u05dc","and be exposed as uncircumcised"],["","-",""],["tis\u00b7s\u014d\u00b7w\u1e07","\u05ea\u05b4\u05bc\u05e1\u05bc\u05a3\u05d5\u05b9\u05d1","[will be] turned"],["\u2018\u0101\u00b7le\u00b7\u1e35\u0101,","\u05e2\u05b8\u05dc\u05b6\u0597\u05d9\u05da\u05b8","against you"],["k\u014d\u00b7ws","\u05db\u05bc\u059a\u05d5\u05b9\u05e1","the cup"],["y\u0259\u00b7m\u00een","\u05d9\u05b0\u05de\u05b4\u05a3\u05d9\u05df","of the right hand"],["Yah\u00b7weh,","\u05d9\u05b0\u05d4\u05d5\u05b8\u0594\u05d4","of Yahweh"],["w\u0259\u00b7q\u00ee\u00b7q\u0101\u00b7l\u014d\u00b7wn","\u05d5\u05b0\u05e7\u05b4\u05d9\u05e7\u05b8\u05dc\u0596\u05d5\u05b9\u05df","and utter shame will be"],["\u2018al-","\u05e2\u05b7\u05dc\u05be","on"],["k\u0259\u00b7\u1e07\u014d\u00b7w\u00b7\u1e0fe\u00b7\u1e35\u0101.","\u05db\u05b0\u05bc\u05d1\u05d5\u05b9\u05d3\u05b6\u05bd\u05da\u05b8\u05c3","your glory"],["",".",""]],"Woe to the Chaldeans"],"17":[[["k\u00ee","\u05db\u05b4\u05bc\u05a3\u05d9","For"],["\u1e25\u0103\u00b7mas","\u05d7\u05b2\u05de\u05b7\u05a4\u05e1","the violence [done to]"],["l\u0259\u00b7\u1e07\u0101\u00b7n\u014d\u00b7wn","\u05dc\u05b0\u05d1\u05b8\u05e0\u05d5\u05b9\u05df\u0599","Lebanon"],["y\u0259\u00b7\u1e35as\u00b7se\u00b7k\u0101,","\u05d9\u05b0\u05db\u05b7\u05e1\u05b6\u05bc\u0594\u05da\u05b8\u05bc","will cover you"],["w\u0259\u00b7\u0161\u014d\u1e0f","\u05d5\u05b0\u05e9\u05b9\u05c1\u05a5\u05d3","and the plunder"],["b\u0259\u00b7h\u00ea\u00b7m\u014d\u00b7w\u1e6f","\u05d1\u05b0\u05bc\u05d4\u05b5\u05de\u0596\u05d5\u05b9\u05ea","of beasts"],["",",",""],["y\u0259\u00b7\u1e25\u00ee\u00b7\u1e6fan;","\u05d9\u05b0\u05d7\u05b4\u05d9\u05ea\u05b7\u0591\u05df","[which] made them afraid"],["",",",""],["mid\u00b7d\u0259\u00b7m\u00ea","\u05de\u05b4\u05d3\u05b0\u05bc\u05de\u05b5\u05a4\u05d9","because of blood"],["",",",""],["\u2019\u0101\u00b7\u1e0f\u0101m","\u05d0\u05b8\u05d3\u05b8\u05dd\u0599","of men"],["wa\u00b7\u1e25\u0103\u00b7mas-","\u05d5\u05b7\u05d7\u05b2\u05de\u05b7\u05e1\u05be","and the violence"],["\u2019e\u00b7re\u1e63,","\u05d0\u05b6\u0594\u05e8\u05b6\u05e5","of the land"],["",",",""],["qir\u00b7y\u0101h","\u05e7\u05b4\u05e8\u05b0\u05d9\u05b8\u0596\u05d4","[and] the city"],["",",",""],["w\u0259\u00b7\u1e35\u0101l","\u05d5\u05b0\u05db\u05b8\u05dc\u05be","and of all"],["y\u014d\u00b7\u0161\u0259\u00b7\u1e07\u00ea","\u05d9\u05b9\u05a5\u05e9\u05b0\u05c1\u05d1\u05b5\u05d9","who dwell"],["\u1e07\u0101h.","\u05d1\u05b8\u05bd\u05d4\u05bc\u05c3","in it"],["",".",""],["s","\u05e1",""]],"Woe to the Chaldeans"],"18":[[["m\u0101h-","\u05de\u05b8\u05bd\u05d4\u05be","What"],["h\u014d\u00b7w\u00b7\u2018\u00eel","\u05d4\u05d5\u05b9\u05e2\u05b4\u05a3\u05d9\u05dc","profit is"],["pe\u00b7sel,","\u05e4\u05b6\u05bc\u0597\u05e1\u05b6\u05dc","the image"],["k\u00ee","\u05db\u05b4\u05bc\u05a4\u05d9","that"],["p\u0304\u0259\u00b7s\u0101\u00b7l\u014dw","\u05e4\u05b0\u05e1\u05b8\u05dc\u05d5\u05b9\u0599","should carve it"],["y\u014d\u00b7\u1e63\u0259\u00b7r\u014dw,","\u05d9\u05b9\u05bd\u05e6\u05b0\u05e8\u0594\u05d5\u05b9","its maker"],["mas\u00b7s\u00ea\u00b7\u1e35\u0101h","\u05de\u05b7\u05e1\u05b5\u05bc\u05db\u05b8\u0596\u05d4","the molded image"],["",",",""],["\u016b\u00b7m\u014d\u00b7w\u00b7reh","\u05d5\u05bc\u05de\u05a3\u05d5\u05b9\u05e8\u05b6\u05d4","and a teacher"],["\u0161\u0101\u00b7qer;","\u05e9\u05b8\u05bc\u05c1\u0591\u05e7\u05b6\u05e8","of lies"],["",",",""],["k\u00ee","\u05db\u05b4\u05bc\u05a3\u05d9","that"],["\u1e07\u0101\u00b7\u1e6da\u1e25","\u05d1\u05b8\u05d8\u05b7\u059e\u05d7","should trust"],["y\u014d\u00b7\u1e63\u00ear","\u05d9\u05b9\u05e6\u05b5\u05a4\u05e8","the maker"],["yi\u1e63\u00b7r\u014dw","\u05d9\u05b4\u05e6\u05b0\u05e8\u05d5\u05b9\u0599","of its mold"],["\u2018\u0101\u00b7l\u0101w,","\u05e2\u05b8\u05dc\u05b8\u0594\u05d9\u05d5","in it"],["",",",""],["la\u00b7\u2018\u0103\u00b7\u015b\u014d\u00b7w\u1e6f","\u05dc\u05b7\u05e2\u05b2\u05e9\u05c2\u0596\u05d5\u05b9\u05ea","to make"],["\u2019\u0115\u00b7l\u00ee\u00b7l\u00eem","\u05d0\u05b1\u05dc\u05b4\u05d9\u05dc\u05b4\u05a5\u05d9\u05dd","idols"],["","?",""],["\u2019il\u00b7l\u0259\u00b7m\u00eem.","\u05d0\u05b4\u05dc\u05b0\u05bc\u05de\u05b4\u05bd\u05d9\u05dd\u05c3","mute"],["",".",""],["s","\u05e1",""]],"Woe to the Chaldeans"],"19":[[["h\u014d\u00b7w","\u05d4\u05a3\u05d5\u05b9\u05d9","Woe"],["\u2019\u014d\u00b7m\u00ear","\u05d0\u05b9\u05de\u05b5\u05a4\u05e8","to him who says"],["l\u0101\u00b7\u2018\u00ea\u1e63","\u05dc\u05b8\u05e2\u05b5\u05e5\u0599","to wood"],["",",",""],["h\u0101\u00b7q\u00ee\u00b7\u1e63\u0101h,","\u05d4\u05b8\u05e7\u05b4\u0594\u05d9\u05e6\u05b8\u05d4","Awake"],["","-",""],["\u2018\u016b\u00b7r\u00ee","\u05e2\u0596\u05d5\u05bc\u05e8\u05b4\u05d9","Arise"],["",",",""],["l\u0259\u00b7\u2019e\u00b7\u1e07en","\u05dc\u05b0\u05d0\u05b6\u05a3\u05d1\u05b6\u05df","to stone"],["",",",""],["d\u016b\u00b7m\u0101m;","\u05d3\u05bc\u05d5\u05bc\u05de\u05b8\u0591\u05dd","silent"],["h\u016b","\u05d4\u05a3\u05d5\u05bc\u05d0","it"],["y\u014d\u00b7w\u00b7reh,","\u05d9\u05d5\u05b9\u05e8\u05b6\u0594\u05d4","shall teach"],["","!",""],["hin\u00b7n\u00eah-","\u05d4\u05b4\u05e0\u05b5\u05bc\u05d4\u05be","behold"],["",",",""],["h\u016b,","\u05d4\u0597\u05d5\u05bc\u05d0","it [is]"],["t\u0101\u00b7p\u0304\u016b\u015b","\u05ea\u05b8\u05bc\u05e4\u05d5\u05bc\u05e9\u05c2\u0599","overlaid"],["z\u0101\u00b7h\u0101\u1e07","\u05d6\u05b8\u05d4\u05b8\u05a3\u05d1","with gold"],["w\u0101\u00b7\u1e35e\u00b7sep\u0304,","\u05d5\u05b8\u05db\u05b6\u0594\u05e1\u05b6\u05e3","and silver"],["",",",""],["w\u0259\u00b7\u1e35\u0101l","\u05d5\u05b0\u05db\u05b8\u05dc\u05be","and yet at all"],["r\u016b\u00b7a\u1e25","\u05e8\u0596\u05d5\u05bc\u05d7\u05b7","breath"],["\u2019\u00ean","\u05d0\u05b5\u05a5\u05d9\u05df","there is no"],["b\u0259\u00b7qir\u00b7b\u014dw.","\u05d1\u05b0\u05bc\u05e7\u05b4\u05e8\u05b0\u05d1\u05bc\u05bd\u05d5\u05b9\u05c3","in it"],["",".",""]],"Woe to the Chaldeans"],"20":[[["Yah\u00b7weh","\u05d5\u05b7\u05bd\u05d9\u05d4\u05d5\u05b8\u0596\u05d4","But Yahweh is"],["b\u0259\u00b7h\u00ea\u00b7\u1e35al","\u05d1\u05b0\u05bc\u05d4\u05b5\u05d9\u05db\u05b7\u05a3\u05dc","in temple"],["",".",""],["q\u0101\u00b7\u1e0f\u0259\u00b7\u0161\u014dw;","\u05e7\u05b8\u05d3\u05b0\u05e9\u05c1\u0591\u05d5\u05b9","His holy"],["has","\u05d4\u05b7\u05a5\u05e1","let keep silence"],["mip\u00b7p\u0101\u00b7n\u0101w","\u05de\u05b4\u05e4\u05b8\u05bc\u05e0\u05b8\u0596\u05d9\u05d5","before Him"],["k\u0101l-","\u05db\u05b8\u05bc\u05dc\u05be","all"],["h\u0101\u00b7\u2019\u0101\u00b7re\u1e63.","\u05d4\u05b8\u05d0\u05b8\u05bd\u05e8\u05b6\u05e5\u05c3","the earth"],["",".",""],["p\u0304","\u05e4",""]],"Woe to the Chaldeans"]},"3":{"1":[[["t\u0259\u00b7p\u0304il\u00b7l\u0101h","\u05ea\u05b0\u05bc\u05e4\u05b4\u05dc\u05b8\u05bc\u0596\u05d4","A prayer"],["la\u00b7\u1e25\u0103\u00b7\u1e07aq\u00b7q\u016bq","\u05dc\u05b7\u05d7\u05b2\u05d1\u05b7\u05e7\u05bc\u05a3\u05d5\u05bc\u05e7","of Habakkuk"],["han\u00b7n\u0101\u00b7\u1e07\u00ee;","\u05d4\u05b7\u05e0\u05b8\u05bc\u05d1\u05b4\u0591\u05d9\u05d0","the prophet"],["\u2018al","\u05e2\u05b7\u0596\u05dc","on"],["\u0161i\u1e21\u00b7y\u014d\u00b7n\u014d\u00b7w\u1e6f.","\u05e9\u05b4\u05c1\u05d2\u05b0\u05d9\u05b9\u05e0\u05bd\u05d5\u05b9\u05ea\u05c3","Shigionoth"],["",".",""]],"Habakkuk's Prayer"],"2":[[["Yah\u00b7weh","\u05d9\u05b0\u05d4\u05d5\u05b8\u0597\u05d4","Yahweh"],["",",",""],["\u0161\u0101\u00b7ma\u2018\u00b7t\u00ee","\u05e9\u05b8\u05c1\u05de\u05b7\u05a3\u05e2\u05b0\u05ea\u05b4\u05bc\u05d9","I have heard"],["\u0161im\u00b7\u2018\u0103\u00b7\u1e35\u0101","\u05e9\u05b4\u05c1\u05de\u05b0\u05e2\u05b2\u05da\u05b8\u05ae","your speech"],["",",",""],["y\u0101\u00b7r\u00ea\u00b7\u1e6f\u00ee","\u05d9\u05b8\u05e8\u05b5\u05d0\u05ea\u05b4\u05d9\u0592","[and] was afraid"],["",".",""],["Yah\u00b7weh","\u05d9\u05b0\u05d4\u05d5\u05b8\u0597\u05d4","Yahweh"],["",",",""],["p\u0101\u00b7\u2018\u0101\u00b7l\u0259\u00b7\u1e35\u0101","\u05e4\u05b8\u05bc\u05bd\u05e2\u05b8\u05dc\u05b0\u05da\u05b8\u0599","Your work"],["b\u0259\u00b7qe\u00b7re\u1e07","\u05d1\u05b0\u05bc\u05e7\u05b6\u05a4\u05e8\u05b6\u05d1","in the midst"],["\u0161\u0101\u00b7n\u00eem","\u05e9\u05b8\u05c1\u05e0\u05b4\u05d9\u05dd\u0599","of the years"],["",",",""],["\u1e25ay\u00b7y\u00ea\u00b7h\u016b,","\u05d7\u05b7\u05d9\u05b5\u05bc\u0594\u05d9\u05d4\u05d5\u05bc","revive"],["b\u0259\u00b7qe\u00b7re\u1e07","\u05d1\u05b0\u05bc\u05e7\u05b6\u05a5\u05e8\u05b6\u05d1","in the midst"],["\u0161\u0101\u00b7n\u00eem","\u05e9\u05b8\u05c1\u05e0\u05b4\u0596\u05d9\u05dd","of the years"],["t\u014d\u00b7w\u00b7\u1e0f\u00ee\u00b7a\u2018;","\u05ea\u05bc\u05d5\u05b9\u05d3\u05b4\u0591\u05d9\u05e2\u05b7","make [it] known"],["","-",""],["b\u0259\u00b7r\u014d\u00b7\u1e21ez","\u05d1\u05b0\u05bc\u05e8\u05b9\u0596\u05d2\u05b6\u05d6","in wrath"],["ra\u00b7\u1e25\u00eam","\u05e8\u05b7\u05d7\u05b5\u05a5\u05dd","mercy"],["tiz\u00b7k\u014d\u00b7wr.","\u05ea\u05b4\u05bc\u05d6\u05b0\u05db\u05bc\u05bd\u05d5\u05b9\u05e8\u05c3","remember"],["",".",""]],"Habakkuk's Prayer"],"3":[[["\u2019\u0115\u00b7l\u014d\u00b7w\u00b7ha","\u05d0\u05b1\u05dc\u0599\u05d5\u05b9\u05d4\u05b7\u0599\u202a\u202c","God"],["mit\u00b7t\u00ea\u00b7m\u0101n","\u05de\u05b4\u05ea\u05b5\u05bc\u05d9\u05de\u05b8\u05a3\u05df","from Teman"],["y\u0101\u00b7\u1e07\u014d\u00b7w,","\u05d9\u05b8\u05d1\u0594\u05d5\u05b9\u05d0","came"],["w\u0259\u00b7q\u0101\u00b7\u1e0f\u014d\u00b7w\u014d\u0161","\u05d5\u05b0\u05e7\u05b8\u05d3\u05a5\u05d5\u05b9\u05e9\u05c1","and the Holy one"],["m\u00ea\u00b7har-","\u05de\u05b5\u05bd\u05d4\u05b7\u05e8\u05be","from Mount"],["p\u0101\u00b7r\u0101n","\u05e4\u05b8\u05bc\u05d0\u05e8\u05b8\u0596\u05df","Paran"],["",".",""],["se\u00b7l\u0101h;","\u05e1\u05b6\u0591\u05dc\u05b8\u05d4","Selah"],["",".",""],["kis\u00b7s\u0101h","\u05db\u05b4\u05bc\u05e1\u05b8\u05bc\u05a4\u05d4","Covered"],["\u0161\u0101\u00b7ma\u00b7yim","\u05e9\u05b8\u05c1\u05de\u05b7\u0599\u05d9\u05b4\u05dd\u0599","the heavens"],["",",",""],["h\u014d\u00b7w\u00b7\u1e0f\u014dw,","\u05d4\u05d5\u05b9\u05d3\u0594\u05d5\u05b9","His glory"],["\u016b\u00b7\u1e6f\u0259\u00b7hil\u00b7l\u0101\u00b7\u1e6f\u014dw","\u05d5\u05bc\u05ea\u05b0\u05d4\u05b4\u05dc\u05b8\u05bc\u05ea\u0596\u05d5\u05b9","and His praise"],["m\u0101\u00b7l\u0259\u00b7\u2019\u0101h","\u05de\u05b8\u05dc\u05b0\u05d0\u05b8\u05a5\u05d4","was full"],["h\u0101\u00b7\u2019\u0101\u00b7re\u1e63.","\u05d4\u05b8\u05d0\u05b8\u05bd\u05e8\u05b6\u05e5\u05c3","of the earth"],["",".",""]],"Habakkuk's Prayer"],"4":[[["w\u0259\u00b7n\u014d\u00b7\u1e21ah","\u05d5\u05b0\u05e0\u05b9\u0599\u05d2\u05b7\u05d4\u05bc\u0599","And [His] brightness"],["k\u0101\u00b7\u2019\u014d\u00b7wr","\u05db\u05b8\u05bc\u05d0\u05a3\u05d5\u05b9\u05e8","like the light"],["","-",""],["tih\u00b7yeh,","\u05ea\u05b4\u05bc\u05bd\u05d4\u05b0\u05d9\u05b6\u0594\u05d4","was"],["qar\u00b7na\u00b7yim","\u05e7\u05b7\u05e8\u05b0\u05e0\u05b7\u05a5\u05d9\u05b4\u05dd","He had rays [flashing]"],["m\u00ee\u00b7y\u0101\u00b7\u1e0f\u014dw","\u05de\u05b4\u05d9\u05b8\u05bc\u05d3\u0596\u05d5\u05b9","from hand"],["",",",""],["l\u014dw;","\u05dc\u0591\u05d5\u05b9","His"],["w\u0259\u00b7\u0161\u0101m","\u05d5\u05b0\u05e9\u05b8\u05c1\u0596\u05dd","and there [was]"],["\u1e25e\u1e07\u00b7y\u014d\u00b7wn","\u05d7\u05b6\u05d1\u05b0\u05d9\u05a5\u05d5\u05b9\u05df","hidden"],["\u2018uz\u00b7z\u014dh","\u05e2\u05bb\u05d6\u05b9\u05bc\u05bd\u05d4\u05c3\u202a\u202c\u202a\u202c","His power"],["",".",""]],"Habakkuk's Prayer"],"5":[[["l\u0259\u00b7p\u0304\u0101\u00b7n\u0101w","\u05dc\u05b0\u05e4\u05b8\u05e0\u05b8\u0596\u05d9\u05d5","Before Him"],["y\u00ea\u00b7le\u1e35","\u05d9\u05b5\u05a3\u05dc\u05b6\u05da\u05b0","went"],["d\u0101\u00b7\u1e07er;","\u05d3\u05b8\u05bc\u0591\u05d1\u05b6\u05e8","pestilence"],["",",",""],["w\u0259\u00b7y\u00ea\u00b7\u1e63\u00ea","\u05d5\u05b0\u05d9\u05b5\u05e6\u05b5\u05a5\u05d0","and followed"],["re\u00b7\u0161ep\u0304","\u05e8\u05b6\u0596\u05e9\u05b6\u05c1\u05e3","fever"],["l\u0259\u00b7ra\u1e21\u00b7l\u0101w.","\u05dc\u05b0\u05e8\u05b7\u05d2\u05b0\u05dc\u05b8\u05bd\u05d9\u05d5\u05c3","at His feet"],["",".",""]],"Habakkuk's Prayer"],"6":[[["\u2018\u0101\u00b7ma\u1e0f","\u05e2\u05b8\u05de\u05b7\u05a3\u05d3 \u05c0","He stood"],["",",",""],["way\u00b7m\u014d\u00b7\u1e0fe\u1e0f","\u05d5\u05b7\u05d9\u05b0\u05de\u05b9\u05a3\u05d3\u05b6\u05d3","and measured"],["\u2019e\u00b7re\u1e63,","\u05d0\u05b6\u0597\u05e8\u05b6\u05e5","the earth"],["","-",""],["r\u0101\u00b7\u2019\u0101h","\u05e8\u05b8\u05d0\u05b8\u05d4\u0599","He looked"],["",",",""],["way\u00b7yat\u00b7t\u00ear","\u05d5\u05b7\u05d9\u05b7\u05bc\u05ea\u05b5\u05bc\u05a3\u05e8","and startled"],["g\u014d\u00b7w\u00b7yim,","\u05d2\u05bc\u05d5\u05b9\u05d9\u05b4\u0594\u05dd","the nations"],["","-",""],["way\u00b7yi\u1e6f\u00b7p\u014d\u00b7\u1e63\u0259\u00b7\u1e63\u016b","\u05d5\u05b7\u05d9\u05b4\u05bc\u05ea\u05b0\u05e4\u05b9\u05bc\u05bd\u05e6\u05b0\u05e6\u05d5\u05bc\u0599","and were scattered"],["",",",""],["har\u00b7r\u00ea-","\u05d4\u05b7\u05e8\u05b0\u05e8\u05b5\u05d9\u05be","the mountains"],["\u2018a\u1e0f,","\u05e2\u05b7\u0594\u05d3","everlasting"],["\u0161a\u00b7\u1e25\u016b","\u05e9\u05b7\u05c1\u05d7\u0596\u05d5\u05bc","bowed"],["",".",""],["gi\u1e07\u00b7\u2018\u014d\u00b7w\u1e6f","\u05d2\u05b4\u05bc\u05d1\u05b0\u05e2\u05a3\u05d5\u05b9\u05ea","The hills"],["\u2018\u014d\u00b7w\u00b7l\u0101m;","\u05e2\u05d5\u05b9\u05dc\u05b8\u0591\u05dd","perpetual"],["h\u0103\u00b7l\u00ee\u00b7\u1e35\u014d\u00b7w\u1e6f","\u05d4\u05b2\u05dc\u05b4\u05d9\u05db\u05a5\u05d5\u05b9\u05ea","ways [are]"],["\u2018\u014d\u00b7w\u00b7l\u0101m","\u05e2\u05d5\u05b9\u05dc\u05b8\u0596\u05dd","everlasting"],["l\u014dw","\u05dc\u05bd\u05d5\u05b9\u05c3","His"],["",".",""]],"Habakkuk's Prayer"],"7":[[["ta\u00b7\u1e25a\u1e6f","\u05ea\u05b7\u05bc\u05a3\u05d7\u05b7\u05ea","In"],["\u2019\u0101\u00b7wen,","\u05d0\u05b8\u0594\u05d5\u05b6\u05df","affliction"],["",",",""],["r\u0101\u00b7\u2019\u00ee\u00b7\u1e6f\u00ee","\u05e8\u05b8\u05d0\u05b4\u0596\u05d9\u05ea\u05b4\u05d9","I saw"],["\u2019\u0101\u00b7ho\u00b7l\u00ea","\u05d0\u05b8\u05d4\u05b3\u05dc\u05b5\u05a3\u05d9","the tents"],["\u1e35\u016b\u00b7\u0161\u0101n;","\u05db\u05d5\u05bc\u05e9\u05b8\u05c1\u0591\u05df","of Cushan"],["yir\u00b7g\u0259\u00b7z\u016bn","\u05d9\u05b4\u05e8\u05b0\u05d2\u05b0\u05bc\u05d6\u0595\u05d5\u05bc\u05df","trembled"],["",".",""],["y\u0259\u00b7r\u00ee\u00b7\u2018\u014d\u00b7w\u1e6f","\u05d9\u05b0\u05e8\u05b4\u05d9\u05e2\u0596\u05d5\u05b9\u05ea","The curtains"],["\u2019e\u00b7re\u1e63","\u05d0\u05b6\u05a5\u05e8\u05b6\u05e5","of the land"],["mi\u1e0f\u00b7y\u0101n.","\u05de\u05b4\u05d3\u05b0\u05d9\u05b8\u05bd\u05df\u05c3","of Midian"],["",".",""],["s","\u05e1",""]],"Habakkuk's Prayer"],"8":[[["h\u0103\u00b7\u1e07in\u00b7h\u0101\u00b7r\u00eem","\u05d4\u05b2\u05d1\u05b4\u05e0\u05b0\u05d4\u05b8\u05e8\u05b4\u05d9\u05dd\u0599","Were with the rivers"],["","?",""],["\u1e25\u0101\u00b7r\u0101h","\u05d7\u05b8\u05e8\u05b8\u05a3\u05d4","[You] displeased"],["Yah\u00b7weh,","\u05d9\u05b0\u05d4\u05d5\u05b8\u0594\u05d4","Yahweh"],["\u2019im","\u05d0\u05b4\u05a4\u05dd","[Was]"],["ban\u00b7n\u0259\u00b7h\u0101\u00b7r\u00eem","\u05d1\u05b7\u05bc\u05e0\u05b0\u05bc\u05d4\u05b8\u05e8\u05b4\u05d9\u05dd\u0599","against the rivers"],["","?",""],["\u2019ap\u00b7pe\u00b7\u1e35\u0101,","\u05d0\u05b7\u05e4\u05b6\u05bc\u0594\u05da\u05b8","Your anger"],["\u2019im-","\u05d0\u05b4\u05dd\u05be","[Was]"],["bay\u00b7y\u0101m","\u05d1\u05b7\u05bc\u05d9\u05b8\u05bc\u0596\u05dd","against the sea"],["",",",""],["\u2018e\u1e07\u00b7r\u0101\u00b7\u1e6fe\u00b7\u1e35\u0101;","\u05e2\u05b6\u05d1\u05b0\u05e8\u05b8\u05ea\u05b6\u0591\u05da\u05b8","Your wrath"],["k\u00ee","\u05db\u05b4\u05bc\u05a4\u05d9","that"],["\u1e6fir\u00b7ka\u1e07","\u05ea\u05b4\u05e8\u05b0\u05db\u05b7\u05bc\u05d1\u0599","You rode"],["\u2018al-","\u05e2\u05b7\u05dc\u05be","on"],["s\u016b\u00b7se\u00b7\u1e35\u0101,","\u05e1\u05d5\u05bc\u05e1\u05b6\u0594\u05d9\u05da\u05b8","Your horses"],["mar\u00b7k\u0259\u00b7\u1e07\u014d\u00b7\u1e6fe\u00b7\u1e35\u0101","\u05de\u05b7\u05e8\u05b0\u05db\u05b0\u05bc\u05d1\u05b9\u05ea\u05b6\u0596\u05d9\u05da\u05b8","Your chariots"],["y\u0259\u00b7\u0161\u016b\u00b7\u2018\u0101h.","\u05d9\u05b0\u05e9\u05c1\u05d5\u05bc\u05e2\u05b8\u05bd\u05d4\u05c3","of salvation"],["","?",""]],"Habakkuk's Prayer"],"9":[[["\u2018er\u00b7y\u0101h","\u05e2\u05b6\u05e8\u05b0\u05d9\u05b8\u05a4\u05d4","quite"],["\u1e6f\u00ea\u00b7\u2018\u014d\u00b7wr","\u05ea\u05b5\u05e2\u05d5\u05b9\u05e8\u0599","was made ready"],["",",",""],["qa\u0161\u00b7te\u00b7\u1e35\u0101,","\u05e7\u05b7\u05e9\u05b0\u05c1\u05ea\u05b6\u05bc\u0594\u05da\u05b8","Your bow"],["\u0161\u0259\u00b7\u1e07u\u00b7\u2018\u014d\u00b7w\u1e6f","\u05e9\u05b0\u05c1\u05d1\u05bb\u05e2\u05a5\u05d5\u05b9\u05ea","was sworn"],["ma\u1e6d\u00b7\u1e6d\u014d\u00b7w\u1e6f","\u05de\u05b7\u05d8\u05bc\u0596\u05d5\u05b9\u05ea","[over Your] arrows"],["",",",""],["\u2019\u014d\u00b7mer","\u05d0\u05b9\u05a3\u05de\u05b6\u05e8","speech"],["",".",""],["se\u00b7l\u0101h;","\u05e1\u05b6\u0591\u05dc\u05b8\u05d4","Selah"],["",".",""],["n\u0259\u00b7h\u0101\u00b7r\u014d\u00b7w\u1e6f","\u05e0\u05b0\u05d4\u05b8\u05e8\u0596\u05d5\u05b9\u05ea","With rivers"],["t\u0259\u00b7\u1e07aq\u00b7qa\u2018-","\u05ea\u05b0\u05bc\u05d1\u05b7\u05e7\u05b7\u05bc\u05e2\u05be","You divided"],["\u2019\u0101\u00b7re\u1e63.","\u05d0\u05b8\u05bd\u05e8\u05b6\u05e5\u05c3","the earth"],["",".",""]],"Habakkuk's Prayer"],"10":[[["r\u0101\u00b7\u2019\u016b\u00b7\u1e35\u0101","\u05e8\u05b8\u05d0\u05a4\u05d5\u05bc\u05da\u05b8","Saw You"],["y\u0101\u00b7\u1e25\u00ee\u00b7l\u016b","\u05d9\u05b8\u05d7\u05b4\u0599\u05d9\u05dc\u05d5\u05bc\u0599","[and] trembled"],["","-",""],["h\u0101\u00b7r\u00eem,","\u05d4\u05b8\u05e8\u05b4\u0594\u05d9\u05dd","the mountains"],["ze\u00b7rem","\u05d6\u05b6\u05a5\u05e8\u05b6\u05dd","the overflowing"],["ma\u00b7yim","\u05de\u05b7\u0596\u05d9\u05b4\u05dd","of the water"],["\u2018\u0101\u00b7\u1e07\u0101r;","\u05e2\u05b8\u05d1\u05b8\u0591\u05e8","passed by"],["","-",""],["n\u0101\u00b7\u1e6fan","\u05e0\u05b8\u05ea\u05b7\u05a4\u05df","uttered"],["t\u0259\u00b7h\u014d\u00b7wm","\u05ea\u05b0\u05bc\u05d4\u05d5\u05b9\u05dd\u0599","the deep"],["q\u014d\u00b7w\u00b7l\u014dw,","\u05e7\u05d5\u05b9\u05dc\u0594\u05d5\u05b9","its voice"],["",",",""],["r\u014d\u00b7wm","\u05e8\u0596\u05d5\u05b9\u05dd","on high"],["y\u0101\u00b7\u1e0f\u00ea\u00b7h\u016b","\u05d9\u05b8\u05d3\u05b5\u05a5\u05d9\u05d4\u05d5\u05bc","its hands"],["n\u0101\u00b7\u015b\u0101.","\u05e0\u05b8\u05e9\u05b8\u05bd\u05c2\u05d0\u05c3","[And] lifted"],["",".",""]],"Habakkuk's Prayer"],"11":[[["\u0161e\u00b7me\u0161","\u05e9\u05b6\u05c1\u05a5\u05de\u05b6\u05e9\u05c1","The sun"],["y\u0101\u00b7r\u00ea\u00b7a\u1e25","\u05d9\u05b8\u05e8\u05b5\u0596\u05d7\u05b7","and moon"],["\u2018\u0101\u00b7ma\u1e0f","\u05e2\u05b8\u05a3\u05de\u05b7\u05d3","stood still"],["z\u0259\u00b7\u1e07u\u00b7l\u0101h;","\u05d6\u05b0\u05d1\u05bb\u0591\u05dc\u05b8\u05d4","in their habitation"],["","-",""],["l\u0259\u00b7\u2019\u014d\u00b7wr","\u05dc\u05b0\u05d0\u05a4\u05d5\u05b9\u05e8","at the light"],["\u1e25i\u1e63\u00b7\u1e63e\u00b7\u1e35\u0101","\u05d7\u05b4\u05e6\u05b6\u05bc\u0599\u05d9\u05da\u05b8\u0599","of Your arrows"],["y\u0259\u00b7hal\u00b7l\u00ea\u00b7\u1e35\u016b,","\u05d9\u05b0\u05d4\u05b7\u05dc\u05b5\u05bc\u0594\u05db\u05d5\u05bc","they went"],["",",",""],["l\u0259\u00b7n\u014d\u00b7\u1e21ah","\u05dc\u05b0\u05e0\u05b9\u0596\u05d2\u05b7\u05d4\u05bc","at the shining"],["b\u0259\u00b7raq","\u05d1\u05b0\u05bc\u05e8\u05b7\u05a5\u05e7","glittering"],["\u1e25\u0103\u00b7n\u00ee\u00b7\u1e6fe\u00b7\u1e35\u0101.","\u05d7\u05b2\u05e0\u05b4\u05d9\u05ea\u05b6\u05bd\u05da\u05b8\u05c3","of Your spear"],["",".",""]],"Habakkuk's Prayer"],"12":[[["b\u0259\u00b7za\u00b7\u2018am","\u05d1\u05b0\u05bc\u05d6\u05b7\u0596\u05e2\u05b7\u05dd","In indignation"],["",",",""],["ti\u1e63\u00b7\u2018a\u1e0f-","\u05ea\u05b4\u05bc\u05e6\u05b0\u05e2\u05b7\u05d3\u05be","You marched through"],["\u2019\u0101\u00b7re\u1e63;","\u05d0\u05b8\u0591\u05e8\u05b6\u05e5","the land"],["b\u0259\u00b7\u2019ap\u0304","\u05d1\u05b0\u05bc\u05d0\u05b7\u0596\u05e3","in anger"],["t\u0101\u00b7\u1e0f\u016b\u0161","\u05ea\u05b8\u05bc\u05d3\u05a5\u05d5\u05bc\u05e9\u05c1","You trampled"],["g\u014d\u00b7w\u00b7yim.","\u05d2\u05bc\u05d5\u05b9\u05d9\u05b4\u05bd\u05dd\u05c3","the nations"],["",".",""]],"Habakkuk's Prayer"],"13":[[["y\u0101\u00b7\u1e63\u0101\u00b7\u1e6f\u0101","\u05d9\u05b8\u05e6\u05b8\u0599\u05d0\u05ea\u05b8\u0599","You went forth"],["l\u0259\u00b7y\u00ea\u00b7\u0161a\u2018","\u05dc\u05b0\u05d9\u05b5\u05a3\u05e9\u05b7\u05c1\u05e2","for the salvation"],["\u2018am\u00b7me\u00b7\u1e35\u0101,","\u05e2\u05b7\u05de\u05b6\u05bc\u0594\u05da\u05b8","of Your people"],["",",",""],["l\u0259\u00b7y\u00ea\u00b7\u0161a\u2018","\u05dc\u05b0\u05d9\u05b5\u0596\u05e9\u05b7\u05c1\u05e2","for salvation"],["\u2019e\u1e6f-","\u05d0\u05b6\u05ea\u05be","with"],["m\u0259\u00b7\u0161\u00ee\u00b7\u1e25e\u00b7\u1e35\u0101;","\u05de\u05b0\u05e9\u05b4\u05c1\u05d9\u05d7\u05b6\u0591\u05da\u05b8","Your Anointed"],["","-",""],["m\u0101\u00b7\u1e25a\u1e63\u00b7t\u0101","\u05de\u05b8\u05d7\u05b7\u05a4\u05e6\u05b0\u05ea\u05b8\u05bc","You struck"],["r\u014d\u0161","\u05e8\u05b9\u05bc\u05d0\u05e9\u05c1\u0599","the head"],["mib\u00b7b\u00ea\u1e6f","\u05de\u05b4\u05d1\u05b5\u05bc\u05a3\u05d9\u05ea","from the house"],["r\u0101\u00b7\u0161\u0101\u2018,","\u05e8\u05b8\u05e9\u05b8\u05c1\u0594\u05e2","of the wicked"],["",",",""],["\u2018\u0101\u00b7r\u014d\u00b7w\u1e6f","\u05e2\u05b8\u05e8\u059b\u05d5\u05b9\u05ea","by laying bare"],["y\u0259\u00b7s\u014d\u00b7w\u1e0f","\u05d9\u05b0\u05e1\u05a5\u05d5\u05b9\u05d3","from foundation"],["\u2018a\u1e0f-","\u05e2\u05b7\u05d3\u05be","to"],["\u1e63aw\u00b7w\u0101r","\u05e6\u05b7\u05d5\u05b8\u05bc\u0596\u05d0\u05e8","neck"],["se\u00b7l\u0101h.","\u05e1\u05b6\u05bd\u05dc\u05b8\u05d4\u05c3","Selah"],["",".",""],["p\u0304","\u05e4",""]],"Habakkuk's Prayer"],"14":[[["n\u0101\u00b7qa\u1e07\u00b7t\u0101","\u05e0\u05b8\u05e7\u05b7\u05a4\u05d1\u05b0\u05ea\u05b8\u05bc","You thrust through"],["\u1e07\u0259\u00b7ma\u1e6d\u00b7\u1e6d\u0101w","\u05d1\u05b0\u05de\u05b7\u05d8\u05b8\u05bc\u05d9\u05d5\u0599","with his own arrows"],["r\u014d\u0161","\u05e8\u05b9\u05a3\u05d0\u05e9\u05c1","the head"],["p\u0259\u00b7r\u0101\u00b7z\u014dw","[\u05e4\u05e8\u05d6\u05d5]","of"],["p\u0259\u00b7r\u0101\u00b7z\u0101w,","(\u05e4\u05b0\u05bc\u05e8\u05b8\u05d6\u05b8\u0594\u05d9\u05d5)","his villages"],["",".",""],["yis\u00b7\u2018\u0103\u00b7r\u016b","\u05d9\u05b4\u05e1\u05b0\u05e2\u05b2\u05e8\u0596\u05d5\u05bc","They came out like a whirlwind"],["la\u00b7h\u0103\u00b7p\u0304\u00ee\u00b7\u1e63\u00ea\u00b7n\u00ee;","\u05dc\u05b7\u05d4\u05b2\u05e4\u05b4\u05d9\u05e6\u05b5\u0591\u05e0\u05b4\u05d9","to scatter me"],["\u2018\u0103\u00b7l\u00ee\u00b7\u1e63u\u00b7\u1e6f\u0101m,","\u05e2\u05b2\u05dc\u05b4\u05a3\u05d9\u05e6\u05bb\u05ea\u05b8\u0594\u05dd","their rejoicing was"],["k\u0259\u00b7m\u014dw-","\u05db\u05b0\u05bc\u05de\u05d5\u05b9\u05be","as"],["le\u00b7\u2019\u0115\u00b7\u1e35\u014dl","\u05dc\u05b6\u05d0\u05b1\u05db\u05b9\u05a5\u05dc","like feasting on"],["\u2018\u0101\u00b7n\u00ee","\u05e2\u05b8\u05e0\u05b4\u0596\u05d9","the poor"],["bam\u00b7mis\u00b7t\u0101r.","\u05d1\u05b7\u05bc\u05de\u05b4\u05bc\u05e1\u05b0\u05ea\u05b8\u05bc\u05bd\u05e8\u05c3","in secret"],["",".",""]],"Habakkuk's Prayer"],"15":[[["d\u0101\u00b7ra\u1e35\u00b7t\u0101","\u05d3\u05b8\u05bc\u05e8\u05b7\u05a5\u05db\u05b0\u05ea\u05b8\u05bc","You walked"],["\u1e07ay\u00b7y\u0101m","\u05d1\u05b7\u05d9\u05b8\u05bc\u0596\u05dd","through the sea"],["s\u016b\u00b7se\u00b7\u1e35\u0101;","\u05e1\u05d5\u05bc\u05e1\u05b6\u0591\u05d9\u05da\u05b8","with Your horses"],["",",",""],["\u1e25\u014d\u00b7mer","\u05d7\u05b9\u0596\u05de\u05b6\u05e8","Through the heap"],["ma\u00b7yim","\u05de\u05b7\u05a5\u05d9\u05b4\u05dd","of waters"],["rab\u00b7b\u00eem.","\u05e8\u05b7\u05d1\u05b4\u05bc\u05bd\u05d9\u05dd\u05c3","great"],["",".",""]],"Habakkuk's Prayer"],"16":[[["\u0161\u0101\u00b7ma\u2018\u00b7t\u00ee","\u05e9\u05b8\u05c1\u05de\u05b7\u05a3\u05e2\u05b0\u05ea\u05b4\u05bc\u05d9 \u05c0","When I heard"],["",",",""],["wat\u00b7tir\u00b7gaz","\u05d5\u05b7\u05ea\u05b4\u05bc\u05e8\u05b0\u05d2\u05b7\u05bc\u05a3\u05d6","and trembled"],["","-",""],["bi\u1e6d\u00b7n\u00ee,","\u05d1\u05b4\u05bc\u05d8\u05b0\u05e0\u05b4\u0597\u05d9","my body"],["l\u0259\u00b7q\u014d\u00b7wl","\u05dc\u05b0\u05e7\u05d5\u05b9\u05dc\u0599","at the voice"],["","-",""],["\u1e63\u0101\u00b7l\u0103\u00b7l\u016b","\u05e6\u05b8\u05dc\u05b2\u05dc\u05a3\u05d5\u05bc","quivered"],["\u015b\u0259\u00b7p\u0304\u0101\u00b7\u1e6fay,","\u05e9\u05b0\u05c2\u05e4\u05b8\u05ea\u05b7\u0594\u05d9","My lips"],["y\u0101\u00b7\u1e07\u014d\u00b7w","\u05d9\u05b8\u05d1\u05a5\u05d5\u05b9\u05d0","entered"],["r\u0101\u00b7q\u0101\u1e07","\u05e8\u05b8\u05e7\u05b8\u059b\u05d1","Rottenness"],["ba\u00b7\u2018\u0103\u00b7\u1e63\u0101\u00b7may","\u05d1\u05b7\u05bc\u05e2\u05b2\u05e6\u05b8\u05de\u05b7\u0596\u05d9","my bones"],["",",",""],["w\u0259\u00b7\u1e6fa\u1e25\u00b7tay","\u05d5\u05b0\u05ea\u05b7\u05d7\u05b0\u05ea\u05b7\u05bc\u05a3\u05d9","and in myself"],["\u2019er\u00b7g\u0101z;","\u05d0\u05b6\u05e8\u05b0\u05d2\u05b8\u05bc\u0591\u05d6","I trembled"],["\u2019\u0103\u00b7\u0161er","\u05d0\u05b2\u05e9\u05b6\u05c1\u05a4\u05e8","that"],["\u2019\u0101\u00b7n\u016b\u00b7a\u1e25","\u05d0\u05b8\u05e0\u0599\u05d5\u05bc\u05d7\u05b7\u0599","I might rest"],["l\u0259\u00b7y\u014d\u00b7wm","\u05dc\u05b0\u05d9\u05a3\u05d5\u05b9\u05dd","in the day"],["\u1e63\u0101\u00b7r\u0101h,","\u05e6\u05b8\u05e8\u05b8\u0594\u05d4","of trouble"],["",",",""],["la\u00b7\u2018\u0103\u00b7l\u014d\u00b7w\u1e6f","\u05dc\u05b7\u05e2\u05b2\u05dc\u0596\u05d5\u05b9\u05ea","when he comes up"],["l\u0259\u00b7\u2018am","\u05dc\u05b0\u05e2\u05b7\u05a5\u05dd","to the people"],["",",",""],["y\u0259\u00b7\u1e21\u016b\u00b7\u1e0fen\u00b7n\u016b.","\u05d9\u05b0\u05d2\u05d5\u05bc\u05d3\u05b6\u05bd\u05e0\u05bc\u05d5\u05bc\u05c3","He will invade them with his troops"],["",".",""]],"Habakkuk Rejoices"],"17":[[["k\u00ee-","\u05db\u05b4\u05bc\u05bd\u05d9\u05be","Though"],["\u1e6f\u0259\u00b7\u2019\u00ea\u00b7n\u0101h","\u05ea\u05b0\u05d0\u05b5\u05e0\u05b8\u05a3\u05d4","the fig tree"],["l\u014d-","\u05dc\u05b9\u05bd\u05d0\u05be","not"],["\u1e6fip\u0304\u00b7r\u0101\u1e25,","\u05ea\u05b4\u05e4\u05b0\u05e8\u05b8\u0597\u05d7","may blossom"],["",",",""],["w\u0259\u00b7\u2019\u00ean","\u05d5\u05b0\u05d0\u05b5\u05a4\u05d9\u05df","and no"],["y\u0259\u00b7\u1e07\u016bl","\u05d9\u05b0\u05d1\u05d5\u05bc\u05dc\u0599","fruit be"],["bag\u00b7g\u0259\u00b7p\u0304\u0101\u00b7n\u00eem,","\u05d1\u05b7\u05bc\u05d2\u05b0\u05bc\u05e4\u05b8\u05e0\u05b4\u0594\u05d9\u05dd","on the vines"],["","-",""],["ki\u00b7\u1e25\u00ea\u0161","\u05db\u05b4\u05bc\u05d7\u05b5\u05e9\u05c1\u0599","Though may fail"],["",",",""],["ma\u00b7\u2018\u0103\u00b7\u015b\u00eah-","\u05de\u05b7\u05e2\u05b2\u05e9\u05b5\u05c2\u05d4\u05be","the labor"],["za\u00b7yi\u1e6f,","\u05d6\u05b7\u0594\u05d9\u05b4\u05ea","of the olive"],["\u016b\u00b7\u0161\u0259\u00b7\u1e0f\u00ea\u00b7m\u014d\u00b7w\u1e6f","\u05d5\u05bc\u05e9\u05b0\u05c1\u05d3\u05b5\u05de\u0596\u05d5\u05b9\u05ea","and the fields"],["l\u014d-","\u05dc\u05b9\u05d0\u05be","no"],["\u2018\u0101\u00b7\u015b\u0101h","\u05e2\u05b8\u05a3\u05e9\u05b8\u05c2\u05d4","yield"],["\u2019\u014d\u00b7\u1e35el;","\u05d0\u05b9\u0591\u05db\u05b6\u05dc","food"],["","-",""],["g\u0101\u00b7zar","\u05d2\u05b8\u05bc\u05d6\u05b7\u05a4\u05e8","Though may be cut off"],["mim\u00b7mi\u1e35\u00b7l\u0101h","\u05de\u05b4\u05de\u05b4\u05bc\u05db\u05b0\u05dc\u05b8\u05d4\u0599","from the fold"],["",",",""],["\u1e63\u014dn,","\u05e6\u05b9\u0594\u05d0\u05df","the flock"],["w\u0259\u00b7\u2019\u00ean","\u05d5\u05b0\u05d0\u05b5\u05a5\u05d9\u05df","and there be no"],["b\u0101\u00b7q\u0101r","\u05d1\u05b8\u05bc\u05e7\u05b8\u0596\u05e8","herd"],["b\u0101\u00b7r\u0259\u00b7p\u0304\u0101\u00b7\u1e6f\u00eem.","\u05d1\u05b8\u05bc\u05e8\u05b0\u05e4\u05b8\u05ea\u05b4\u05bd\u05d9\u05dd\u05c3","in the stalls"],["",",",""]],"Habakkuk Rejoices"],"18":[[["wa\u00b7\u2019\u0103\u00b7n\u00ee","\u05d5\u05b7\u05d0\u05b2\u05e0\u05b4\u0596\u05d9","and yet I"],["Yah\u00b7weh","\u05d1\u05b7\u05bc\u05d9\u05d4\u05d5\u05b8\u05a3\u05d4","in Yahweh"],["",",",""],["\u2019e\u2018\u00b7l\u014d\u00b7w\u00b7z\u0101h;","\u05d0\u05b6\u05e2\u05b0\u05dc\u0591\u05d5\u05b9\u05d6\u05b8\u05d4","will rejoice"],["\u2019\u0101\u00b7\u1e21\u00ee\u00b7l\u0101h","\u05d0\u05b8\u05d2\u05b4\u0596\u05d9\u05dc\u05b8\u05d4","I will joy"],["b\u00ea\u00b7l\u014d\u00b7h\u00ea","\u05d1\u05b5\u05bc\u05d0\u05dc\u05b9\u05d4\u05b5\u05a5\u05d9","in the God"],["yi\u0161\u00b7\u2018\u00ee.","\u05d9\u05b4\u05e9\u05b0\u05c1\u05e2\u05b4\u05bd\u05d9\u05c3","of my salvation"],["",".",""]],"Habakkuk Rejoices"],"19":[[["Yah\u00b7weh","\u05d9\u05b0\u05d4\u05d5\u05b4\u05a4\u05d4\u05bc\u202a\u202c\u202a\u202c","GOD"],["\u2019\u0103\u00b7\u1e0f\u014d\u00b7n\u0101y","\u05d0\u05b2\u05d3\u05b9\u05e0\u05b8\u05d9\u0599","the Lord is"],["\u1e25\u00ea\u00b7l\u00ee,","\u05d7\u05b5\u05d9\u05dc\u05b4\u0594\u05d9","my strength"],["",",",""],["way\u00b7y\u0101\u00b7\u015bem","\u05d5\u05b7\u05d9\u05b8\u05bc\u05a4\u05e9\u05b6\u05c2\u05dd","and He will make"],["ra\u1e21\u00b7lay","\u05e8\u05b7\u05d2\u05b0\u05dc\u05b7\u05d9\u0599","my feet"],["k\u0101\u00b7\u2019ay\u00b7y\u0101\u00b7l\u014d\u00b7w\u1e6f,","\u05db\u05b8\u05bc\u05bd\u05d0\u05b7\u05d9\u05b8\u05bc\u05dc\u0594\u05d5\u05b9\u05ea","like deer's [feet]"],["w\u0259\u00b7\u2018al","\u05d5\u05b0\u05e2\u05b7\u05a5\u05dc","and on"],["b\u0101\u00b7m\u014d\u00b7w\u00b7\u1e6fay","\u05d1\u05b8\u05bc\u05de\u05d5\u05b9\u05ea\u05b7\u0596\u05d9","my high hills"],["",".",""],["ya\u1e0f\u00b7ri\u00b7\u1e35\u00ea\u00b7n\u00ee;","\u05d9\u05b7\u05d3\u05b0\u05e8\u05b4\u05db\u05b5\u0591\u05e0\u05b4\u05d9","He will make me walk"],["lam\u00b7na\u1e63\u00b7\u1e63\u00ea\u00b7a\u1e25","\u05dc\u05b7\u05de\u05b0\u05e0\u05b7\u05e6\u05b5\u05bc\u0596\u05d7\u05b7","to the Chief Musician"],["bin\u00b7\u1e21\u00ee\u00b7n\u014d\u00b7w\u00b7\u1e6f\u0101y.","\u05d1\u05b4\u05bc\u05e0\u05b0\u05d2\u05b4\u05d9\u05e0\u05d5\u05b9\u05ea\u05b8\u05bd\u05d9\u05c3","with my stringed instruments"],["",".",""]],"Habakkuk Rejoices"]}}